{"data": {"tenders": {"current_page": 216, "data": [{"id": 4010, "name": "\u0420\u0435\u043a\u043e\u043d\u0441\u0442\u0440\u0443\u043a\u0446\u0438\u044f \u0437\u0434\u0430\u043d\u0438\u0438 \u043f\u0440\u043e\u0444\u0435\u0441\u0441\u0438\u043e\u043d\u0430\u043b\u044c\u043d\u043e-\u0442\u0435\u0445\u043d\u0438\u0447\u0435\u0441\u043a\u043e\u0435 \u0443\u0447\u0438\u043b\u0438\u0449\u0435 \u21161 \u041d\u0443\u0440\u0430\u0442\u0438\u043d\u0441\u043a\u043e\u0433\u043e \u0440\u0430\u0439\u043e\u043d\u0430 \u041d\u0430\u0432\u043e\u0438\u0439\u0441\u043a\u043e\u0439 \u043e\u0431\u043b\u0430\u0441\u0442\u0438", "object_type_id": 2, "service_type_id": 2, "complexity_category_id": 2, "category_score_id": 11, "start_price": 459394246, "end_term_work": "2021-07-20", "end_term_work_days": 40, "region_id": 4, "district_id": 44, "address": "\u041d\u0430\u0432\u043e\u0438\u0439 \u0432\u0438\u043b\u043e\u044f\u0442\u0438 \u041d\u0443\u0440\u043e\u0442\u0430 \u0442\u0443\u043c\u0430\u043d\u0438", "phone": "(79) 220-50-03", "financial_source": "\u0426\u0435\u043d\u0442\u0440\u0430\u043b\u0438\u0437\u043e\u0432\u0430\u043d\u043d\u044b\u0439 \u0438 \u043c\u0435\u0441\u0442\u043d\u044b\u0439 \u0431\u044e\u0434\u0436\u0435\u0442", "currency": "UZS", "language": null, "placement_term": "2021-08-10 23:59:59", "placement_term_days": 10, "contact_person": {"position": "navoi-tender@mail.ru", "full_name": "\u0420\u0443\u0441\u0442\u0430\u043c\u043e\u0432 \u041a."}, "additional_information": null, "contract": "contracts/contract-2859.docx", "unique_name": 13932, "psd": "psd/\u043f\u0441\u0434-2859.pdf", "expertise": "expertise/expertise-2859.PDF", "reason_of_deletion": null, "protocol": "pdf/protocol-4010.pdf", "customer_id": 83, "consulting_id": 50, "request_id": 2610, "winner_id": 1018, "reserve_winner_id": 4199, "winner_confirmation": "2", "license": null, "status": "5", "personal_account": null, "created_at": "2021-07-27 08:06:44", "updated_at": "2021-08-21 10:35:24", "winner_doc_id": 21494, "required_percent": "1", "checking_account": "22604000104297337001 \u041c\u0424\u041e 00205 \u0418\u041d\u041d 204775508 \u0410\u041a\u0411 \u0418\u043f\u043e\u0442\u0435\u043a\u0430\u0431\u0430\u043d\u043a \u041d\u0430\u0432\u043e\u0438\u0439\u0441\u043a\u0438\u0439 \u0444\u0438\u043b\u0438\u0430\u043b", "comission_1_checked_date": null, "moderator_checked_date": "2021-06-09 16:30:38", "send_to_commission_at": null, "updated": null, "modified_by": 1902, "finance_moderator_checked_date": "2021-06-10 12:09:06", "placement_term_left": null, "reason_of_deletion_file": null, "transaction_date": "2021-08-21 10:35:24", "customer_fio": null, "show_scores": null, "rejected_offeror_id": null, "t_moderator_date": "2021-06-09 16:23:17", "failed_reason": null, "t_customer_confirmed": null, "t_confirmed_date": null, "old_tender_id": null, "customer_position": null, "customer_address": null, "prikaz": null, "bidders_count": 2, "customer_info": {"id": 83, "name": "\u0412\u0438\u043b\u043e\u044f\u0442 \u043a\u0430\u043f\u0438\u0442\u0430\u043b \u043a\u0443\u0440\u0438\u043b\u0438\u0448 \u0438\u043d\u0436\u0438\u043d\u0438\u0440\u0438\u043d\u0433 \u043a\u043e\u043c\u043f\u0430\u043d\u0438\u044f\u0441\u0438", "organisation_director": "\u0422\u0423\u0420\u0414\u0418\u0415\u0412 \u0410\u041b\u0418\u0428\u0415\u0420 \u0411\u0410\u0425\u0420\u041e\u041c\u041e\u0412\u0418\u0427"}, "region": {"id": 4, "name": "\u041d\u0430\u0432\u043e\u0438\u0439\u0441\u043a\u0430\u044f \u043e\u0431\u043b\u0430\u0441\u0442\u044c", "created_at": "2020-12-07T05:50:45.000000Z", "updated_at": "2020-12-07T05:50:45.000000Z", "deleted_at": null}}, {"id": 4009, "name": "\u0421\u0442\u0440\u043e\u0438\u0442\u0435\u043b\u044c\u0441\u0442\u0432\u043e \u043a\u0438\u0441\u043b\u043e\u0440\u043e\u0434\u043d\u043e\u0439 \u0441\u0442\u0430\u043d\u0446\u0438\u0438 \u0434\u043b\u044f \u043e\u0431\u043b\u0430\u0441\u0442\u043d\u043e\u0439 \u0434\u0435\u0442\u0441\u043a\u043e\u0439 \u0438\u043d\u0444\u0435\u043a\u0446\u0438\u043e\u043d\u043d\u043e\u0439 \u0431\u043e\u043b\u044c\u043d\u0438\u0446\u044b \u0432 \u0433\u043e\u0440\u043e\u0434\u0435 \u041d\u0430\u0432\u043e\u0438\u0439 \u041d\u0430\u0432\u043e\u0438\u0439\u0441\u043a\u043e\u0439 \u043e\u0431\u043b\u0430\u0441\u0442\u0438", "object_type_id": 2, "service_type_id": 3, "complexity_category_id": 2, "category_score_id": 9, "start_price": 362236975, "end_term_work": "2021-08-07", "end_term_work_days": 30, "region_id": 4, "district_id": 176, "address": "\u041d\u0430\u0432\u043e\u0438\u0439 \u0432\u0438\u043b\u043e\u044f\u0442\u0438 \u041d\u0430\u0432\u043e\u0438\u0439 \u0448\u0430\u0445\u0440\u0438", "phone": "(79) 220-50-03", "financial_source": "\u041c\u0435\u0441\u0442\u043d\u044b\u0439 \u0431\u044e\u0434\u0436\u0435\u0442", "currency": "UZS", "language": null, "placement_term": "2021-08-10 23:59:59", "placement_term_days": 10, "contact_person": {"position": "navoi-tender@mail.ru", "full_name": "\u0423\u043c\u0430\u0440\u043e\u0432 \u0420."}, "additional_information": "null", "contract": "contracts/contract-3693.docx", "unique_name": 13931, "psd": "psd/\u043f\u0441\u0434-3693.zip", "expertise": "expertise/expertise-3693.pdf", "reason_of_deletion": null, "protocol": "pdf/protocol-4009.pdf", "customer_id": 83, "consulting_id": 50, "request_id": 3151, "winner_id": null, "reserve_winner_id": null, "winner_confirmation": null, "license": null, "status": "29", "personal_account": null, "created_at": "2021-07-27 08:06:30", "updated_at": "2021-08-23 10:12:13", "winner_doc_id": null, "required_percent": "1", "checking_account": "22604000104297337001 \u041c\u0424\u041e 00205 \u0418\u041d\u041d 204775508 \u0410\u041a\u0411 \u0418\u043f\u043e\u0442\u0435\u043a\u0430\u0431\u0430\u043d\u043a \u041d\u0430\u0432\u043e\u0438\u0439\u0441\u043a\u0438\u0439 \u0444\u0438\u043b\u0438\u0430\u043b", "comission_1_checked_date": null, "moderator_checked_date": "2021-07-07 17:13:54", "send_to_commission_at": null, "updated": null, "modified_by": 1902, "finance_moderator_checked_date": "2021-07-07 17:24:31", "placement_term_left": null, "reason_of_deletion_file": null, "transaction_date": "2021-08-23 10:12:13", "customer_fio": null, "show_scores": null, "rejected_offeror_id": null, "t_moderator_date": "2021-07-07 15:41:38", "failed_reason": null, "t_customer_confirmed": null, "t_confirmed_date": null, "old_tender_id": null, "customer_position": null, "customer_address": null, "prikaz": null, "bidders_count": 3, "customer_info": {"id": 83, "name": "\u0412\u0438\u043b\u043e\u044f\u0442 \u043a\u0430\u043f\u0438\u0442\u0430\u043b \u043a\u0443\u0440\u0438\u043b\u0438\u0448 \u0438\u043d\u0436\u0438\u043d\u0438\u0440\u0438\u043d\u0433 \u043a\u043e\u043c\u043f\u0430\u043d\u0438\u044f\u0441\u0438", "organisation_director": "\u0422\u0423\u0420\u0414\u0418\u0415\u0412 \u0410\u041b\u0418\u0428\u0415\u0420 \u0411\u0410\u0425\u0420\u041e\u041c\u041e\u0412\u0418\u0427"}, "region": {"id": 4, "name": "\u041d\u0430\u0432\u043e\u0438\u0439\u0441\u043a\u0430\u044f \u043e\u0431\u043b\u0430\u0441\u0442\u044c", "created_at": "2020-12-07T05:50:45.000000Z", "updated_at": "2020-12-07T05:50:45.000000Z", "deleted_at": null}}, {"id": 4008, "name": "\u0421\u0442\u0440\u043e\u0438\u0442\u0435\u043b\u044c\u0441\u0442\u0432\u043e \u0441\u0438\u0441\u0442\u0435\u043c\u044b \u0438\u0440\u0440\u0438\u0433\u0430\u0446\u0438\u0438-\u043c\u0435\u043b\u0438\u043e\u0440\u0430\u0446\u0438\u0438 \u0432 \u0446\u0435\u043b\u044f\u0445 \u0438\u0441\u043f\u043e\u043b\u044c\u0437\u043e\u0432\u0430\u043d\u0438\u0435 \u043e\u0431\u043e\u0440\u043e\u0442\u043e\u043c \u0437\u0435\u043c\u043b\u0438 \u041e\u041e\u041e \"\u041a\u0443\u043c\u0443\u0448 \u041a\u0430\u043b\u0430\u0432\u0430 \u0410\u0433\u0440\u043e\" \u043d\u0430 \u0442\u0435\u0440\u0440\u0438\u0442\u043e\u0440\u0438\u0438 \"\u041a\u0443\u043b\u043e\u043d\u0447\u0438\" \u0432 \u041a\u0430\u0440\u0430\u043a\u0443\u043b\u0441\u043a\u043e\u043c \u0440\u0430\u0439\u043e\u043d\u0435 \u0411\u0443\u0445\u0430\u0440\u0441\u043a\u043e\u0439 \u043e\u0431\u043b\u0430\u0441\u0442\u0438", "object_type_id": 4, "service_type_id": 3, "complexity_category_id": 3, "category_score_id": 8, "start_price": 2593169239, "end_term_work": "2022-04-23", "end_term_work_days": 270, "region_id": 2, "district_id": 23, "address": "\u049a\u043e\u0440\u0430\u043a\u045e\u043b \u0442\u0443\u043c\u0430\u043d\u0438 \"\u049a\u0443\u043b\u043e\u043d\u0447\u0438\" \u04b3\u0443\u0434\u0443\u0434\u0438\u0434\u0430", "phone": "(91) 923-58-72", "financial_source": "\u0437\u0430 \u0441\u0447\u0451\u0442 \u0441\u0440\u0435\u0434\u0441\u0442\u0432 \u043c\u0435\u0441\u0442\u043d\u043e\u0433\u043e \u0431\u044e\u0434\u0436\u0435\u0442\u0430", "currency": "UZS", "language": null, "placement_term": "2021-08-10 23:59:59", "placement_term_days": 10, "contact_person": {"position": "kafiyat79@mail.ru", "full_name": "\u0411\u043e\u0431\u043e\u0436\u043e\u043d\u043e\u0432 \u0410\u0437\u0438\u0437"}, "additional_information": "\"\u0422\u0430\u043d\u043b\u043e\u0432 \u0441\u0430\u0432\u0434\u043e\u043b\u0430\u0440\u0438\u0434\u0430 \u0438\u0448\u0442\u0438\u0440\u043e\u043a \u044d\u0442\u0438\u0448 \u0431\u0443\u044e\u0440\u0442\u043c\u0430\u0441\u0438\u043d\u0438 \u0442\u0430\u044a\u043c\u0438\u043d\u043b\u0430\u0448 \u0448\u0430\u043a\u043b\u0438 \u0431\u0430\u043d\u043a \u043a\u0430\u0444\u043e\u043b\u0430\u0442\u0438 \u0442\u0430\u0440\u0442\u0438\u0431\u0438\u0434\u0430 \u0451\u043a\u0438 \u043e\u0431\u044a\u0435\u043a\u0442\u043d\u0438\u043d\u0433 1% \u043c\u0438\u049b\u0434\u043e\u0440\u0438\u0434\u0430\u0433\u0438 \u0441\u0443\u043c\u043c\u0430\u043d\u0438 \u0444\u0430\u049b\u0430\u0442 \u0431\u0443\u044e\u0440\u0442\u043c\u0430\u0447\u0438\u043d\u0438\u043d\u0433 \u043c\u0430\u0445\u0441\u0443\u0441 \u04b3\u0438\u0441\u043e\u0431 \u0440\u0430\u049b\u0430\u043c\u0438\u0433\u0430 \u045e\u0442\u043a\u0430\u0437\u0438\u0448 \u0432\u0430 \u0442\u045e\u043b\u0430\u043d\u0433\u0430\u043d\u043b\u0438\u043a \u0442\u045e\u0493\u0440\u0438\u0441\u0438\u0434\u0430\u0433\u0438 \u0442\u045e\u043b\u043e\u0432 \u0442\u043e\u043f\u0448\u0438\u0440\u0438\u049b\u043d\u043e\u043c\u0430\u0441\u0438 \u043d\u0443\u0441\u0445\u0430\u0441\u0438\u043d\u0438 \u0431\u0438\u0440\u0438\u043a\u0442\u0438\u0440\u0438\u043b\u0430\u0434\u0438. \u0411\u0443\u044e\u0440\u0442\u043c\u0430\u0447\u0438 \u0445\u0438\u0441\u043e\u0431 \u0440\u0430\u049b\u0430\u043c\u0438: \u0410\u0422\u0411 \u201c\u0422\u0443\u0440\u043e\u043d \u0431\u0430\u043d\u043a\u201d \u0411\u0443\u0445\u043e\u0440\u043e \u0444\u0438\u043b\u0438\u0430\u043b\u0438 \u0425/\u0440:22604000900672547001; \u041c\u0424\u041e:00111 \u0418\u041d\u041d: 203269804. \u0410\u0439\u043b\u0430\u043d\u043c\u0430 \u043c\u0430\u0431\u043b\u0430\u0493\u043b\u0430\u0440 \u043e\u0431\u044a\u0435\u043a\u0442 \u0431\u043e\u0448\u043b\u0430\u043d\u0493\u0438\u0447 \u043d\u0430\u0440\u0445\u0438\u043d\u0438\u043d\u0433 20% \u0434\u0430\u043d \u043a\u0430\u043c \u043c\u0438\u049b\u0434\u043e\u0440\u0438\u043d\u0438 \u0442\u0430\u0448\u043a\u0438\u043b \u044d\u0442\u0433\u0430\u043d \u04b3\u043e\u043b\u043b\u0430\u0440\u0434\u0430, \u0438\u0448\u0442\u0438\u0440\u043e\u043a\u0447\u0438 \u0430\u0439\u043b\u0430\u043d\u043c\u0430 \u043c\u0430\u0431\u043b\u0430\u0493\u043b\u0430\u0440\u0438 \u043c\u0430\u0432\u0436\u0443\u0434\u043b\u0438\u0433\u0438 \u04b3\u0430\u049b\u0438\u0434\u0430\u0433\u0438 \u0431\u0430\u043d\u043a \u0442\u0430\u0441\u0434\u0438\u049b\u043b\u0430\u0433\u0430\u043d \u043c\u0430\u044a\u043b\u0443\u043c\u043e\u0442\u043d\u043e\u043c\u0430\u043d\u0438 \u0432\u0430 \u0435\u0442\u043c\u0430\u0451\u0442\u0433\u0430\u043d \u0441\u0443\u043c\u043c\u0430\u0433\u0430 \u0431\u0430\u043d\u043a \u043a\u0430\u0444\u0438\u043b\u043b\u0438\u0433\u0438\u043d\u0438 \u0431\u0438\u0440\u0438\u043a\u0442\u0438\u0440\u0430\u0434\u0438 (20 \u0444\u043e\u0438\u0437).\n\u041e\u0431\u044a\u0435\u043a\u0442\u0434\u0430 \u0438\u0445\u0442\u0438\u0441\u043e\u0441\u043b\u0430\u0448\u0442\u0438\u0440\u0438\u043b\u0433\u0430\u043d \u0442\u0430\u0448\u043a\u0438\u043b\u043e\u0442\u043b\u0430\u0440 \u049b\u0430\u0442\u043d\u0430\u0448\u0438\u0448\u043b\u0430\u0440\u0438 \u0442\u0430\u043b\u0430\u0431 \u049b\u0438\u043b\u0438\u043d\u0430\u0434\u0438.\"", "contract": "contracts/contract-4008.doc", "unique_name": 13930, "psd": "psd/\u043f\u0441\u0434-4008.rar", "expertise": "expertise/expertise-4008.pdf", "reason_of_deletion": null, "protocol": "pdf/protocol-4008.pdf", "customer_id": 324, "consulting_id": 3007, "request_id": 3421, "winner_id": null, "reserve_winner_id": null, "winner_confirmation": null, "license": null, "status": "29", "personal_account": null, "created_at": "2021-07-27 02:52:52", "updated_at": "2021-08-11 10:09:26", "winner_doc_id": null, "required_percent": "1", "checking_account": "22604000900672547001 \u041c\u0424\u041e -00111", "comission_1_checked_date": null, "moderator_checked_date": "2021-07-27 09:39:20", "send_to_commission_at": null, "updated": null, "modified_by": 1902, "finance_moderator_checked_date": "2021-07-27 13:52:12", "placement_term_left": null, "reason_of_deletion_file": null, "transaction_date": "2021-08-11 10:09:26", "customer_fio": null, "show_scores": null, "rejected_offeror_id": null, "t_moderator_date": "2021-07-27 02:57:06", "failed_reason": null, "t_customer_confirmed": null, "t_confirmed_date": null, "old_tender_id": null, "customer_position": null, "customer_address": null, "prikaz": null, "bidders_count": 0, "customer_info": {"id": 324, "name": "\u0413\u0423\u041f BUXOROSUVQURILISHINVEST", "organisation_director": "\u041a\u0410\u0414\u0418\u0420\u041e\u0412 \u041e\u041b\u0418\u041c \u0417\u0410\u0418\u0420\u041e\u0412\u0418\u0427"}, "region": {"id": 2, "name": "\u0411\u0443\u0445\u0430\u0440\u0441\u043a\u0430\u044f \u043e\u0431\u043b\u0430\u0441\u0442\u044c", "created_at": "2020-12-07T05:48:11.000000Z", "updated_at": "2020-12-07T05:48:11.000000Z", "deleted_at": null}}, {"id": 4007, "name": "\u0421\u0442\u0440\u043e\u0438\u0442\u0435\u043b\u044c\u0441\u0442\u0432\u043e \u0441\u0438\u0441\u0442\u0435\u043c\u044b \u0438\u0440\u0440\u0438\u0433\u0430\u0446\u0438\u0438-\u043c\u0435\u043b\u0438\u043e\u0440\u0430\u0446\u0438\u0438 \u0432 \u0446\u0435\u043b\u044f\u0445 \u0438\u0441\u043f\u043e\u043b\u044c\u0437\u043e\u0432\u0430\u043d\u0438\u0435 \u043e\u0431\u043e\u0440\u043e\u0442\u043e\u043c \u0437\u0435\u043c\u043b\u0438 \u041e\u041e\u041e \"DCN CRLUSTER \u0410\u0433\u0440\u043e\u043a\u043e\u043c\u043f\u043b\u0435\u043a\u0441\" \u043d\u0430 \u0442\u0435\u0440\u0440\u0438\u0442\u043e\u0440\u0438\u0438 \"\u041a\u043e\u043a\u0438\u0448\u0442\u0443\u0432\u043e\u043d\" \u0432 \u0420\u043e\u043c\u0438\u0442\u0430\u043d\u0441\u043a\u043e\u043c \u0440\u0430\u0439\u043e\u043d\u0435 \u0411\u0443\u0445\u0430\u0440\u0441\u043a\u043e\u0439 \u043e\u0431\u043b\u0430\u0441\u0442\u0438", "object_type_id": 4, "service_type_id": 3, "complexity_category_id": 3, "category_score_id": 8, "start_price": 3358567644, "end_term_work": "2022-04-23", "end_term_work_days": 270, "region_id": 2, "district_id": 26, "address": "\u0420\u043e\u043c\u0438\u0442\u0430\u043d \u0442\u0443\u043c\u0430\u043d\u0438 \"\u049a\u043e\u049b\u0438\u0448\u0442\u0443\u0432\u043e\u043d\"\" \u04b3\u0443\u0434\u0443\u0434\u0438\u0434\u0430", "phone": "(91) 923-58-72", "financial_source": "\u0437\u0430 \u0441\u0447\u0451\u0442 \u0441\u0440\u0435\u0434\u0441\u0442\u0432 \u043c\u0435\u0441\u0442\u043d\u043e\u0433\u043e \u0431\u044e\u0434\u0436\u0435\u0442\u0430", "currency": "UZS", "language": null, "placement_term": "2021-08-10 23:59:59", "placement_term_days": 10, "contact_person": {"position": "kafiyat79@mail.ru", "full_name": "\u0411\u043e\u0431\u043e\u0436\u043e\u043d\u043e\u0432 \u0410\u0437\u0438\u0437"}, "additional_information": "\"\u0422\u0430\u043d\u043b\u043e\u0432 \u0441\u0430\u0432\u0434\u043e\u043b\u0430\u0440\u0438\u0434\u0430 \u0438\u0448\u0442\u0438\u0440\u043e\u043a \u044d\u0442\u0438\u0448 \u0431\u0443\u044e\u0440\u0442\u043c\u0430\u0441\u0438\u043d\u0438 \u0442\u0430\u044a\u043c\u0438\u043d\u043b\u0430\u0448 \u0448\u0430\u043a\u043b\u0438 \u0431\u0430\u043d\u043a \u043a\u0430\u0444\u043e\u043b\u0430\u0442\u0438 \u0442\u0430\u0440\u0442\u0438\u0431\u0438\u0434\u0430 \u0451\u043a\u0438 \u043e\u0431\u044a\u0435\u043a\u0442\u043d\u0438\u043d\u0433 1% \u043c\u0438\u049b\u0434\u043e\u0440\u0438\u0434\u0430\u0433\u0438 \u0441\u0443\u043c\u043c\u0430\u043d\u0438 \u0444\u0430\u049b\u0430\u0442 \u0431\u0443\u044e\u0440\u0442\u043c\u0430\u0447\u0438\u043d\u0438\u043d\u0433 \u043c\u0430\u0445\u0441\u0443\u0441 \u04b3\u0438\u0441\u043e\u0431 \u0440\u0430\u049b\u0430\u043c\u0438\u0433\u0430 \u045e\u0442\u043a\u0430\u0437\u0438\u0448 \u0432\u0430 \u0442\u045e\u043b\u0430\u043d\u0433\u0430\u043d\u043b\u0438\u043a \u0442\u045e\u0493\u0440\u0438\u0441\u0438\u0434\u0430\u0433\u0438 \u0442\u045e\u043b\u043e\u0432 \u0442\u043e\u043f\u0448\u0438\u0440\u0438\u049b\u043d\u043e\u043c\u0430\u0441\u0438 \u043d\u0443\u0441\u0445\u0430\u0441\u0438\u043d\u0438 \u0431\u0438\u0440\u0438\u043a\u0442\u0438\u0440\u0438\u043b\u0430\u0434\u0438. \u0411\u0443\u044e\u0440\u0442\u043c\u0430\u0447\u0438 \u0445\u0438\u0441\u043e\u0431 \u0440\u0430\u049b\u0430\u043c\u0438: \u0410\u0422\u0411 \u201c\u0422\u0443\u0440\u043e\u043d \u0431\u0430\u043d\u043a\u201d \u0411\u0443\u0445\u043e\u0440\u043e \u0444\u0438\u043b\u0438\u0430\u043b\u0438 \u0425/\u0440:22604000900672547001; \u041c\u0424\u041e:00111 \u0418\u041d\u041d: 203269804. \u0410\u0439\u043b\u0430\u043d\u043c\u0430 \u043c\u0430\u0431\u043b\u0430\u0493\u043b\u0430\u0440 \u043e\u0431\u044a\u0435\u043a\u0442 \u0431\u043e\u0448\u043b\u0430\u043d\u0493\u0438\u0447 \u043d\u0430\u0440\u0445\u0438\u043d\u0438\u043d\u0433 20% \u0434\u0430\u043d \u043a\u0430\u043c \u043c\u0438\u049b\u0434\u043e\u0440\u0438\u043d\u0438 \u0442\u0430\u0448\u043a\u0438\u043b \u044d\u0442\u0433\u0430\u043d \u04b3\u043e\u043b\u043b\u0430\u0440\u0434\u0430, \u0438\u0448\u0442\u0438\u0440\u043e\u043a\u0447\u0438 \u0430\u0439\u043b\u0430\u043d\u043c\u0430 \u043c\u0430\u0431\u043b\u0430\u0493\u043b\u0430\u0440\u0438 \u043c\u0430\u0432\u0436\u0443\u0434\u043b\u0438\u0433\u0438 \u04b3\u0430\u049b\u0438\u0434\u0430\u0433\u0438 \u0431\u0430\u043d\u043a \u0442\u0430\u0441\u0434\u0438\u049b\u043b\u0430\u0433\u0430\u043d \u043c\u0430\u044a\u043b\u0443\u043c\u043e\u0442\u043d\u043e\u043c\u0430\u043d\u0438 \u0432\u0430 \u0435\u0442\u043c\u0430\u0451\u0442\u0433\u0430\u043d \u0441\u0443\u043c\u043c\u0430\u0433\u0430 \u0431\u0430\u043d\u043a \u043a\u0430\u0444\u0438\u043b\u043b\u0438\u0433\u0438\u043d\u0438 \u0431\u0438\u0440\u0438\u043a\u0442\u0438\u0440\u0430\u0434\u0438 (20 \u0444\u043e\u0438\u0437).\n\u041e\u0431\u044a\u0435\u043a\u0442\u0434\u0430 \u0438\u0445\u0442\u0438\u0441\u043e\u0441\u043b\u0430\u0448\u0442\u0438\u0440\u0438\u043b\u0433\u0430\u043d \u0442\u0430\u0448\u043a\u0438\u043b\u043e\u0442\u043b\u0430\u0440 \u049b\u0430\u0442\u043d\u0430\u0448\u0438\u0448\u043b\u0430\u0440\u0438 \u0442\u0430\u043b\u0430\u0431 \u049b\u0438\u043b\u0438\u043d\u0430\u0434\u0438.\"", "contract": "contracts/contract-4007.doc", "unique_name": 13929, "psd": "psd/\u043f\u0441\u0434-4007.rar", "expertise": "expertise/expertise-4007.pdf", "reason_of_deletion": null, "protocol": "pdf/protocol-4007.pdf", "customer_id": 324, "consulting_id": 3007, "request_id": 3420, "winner_id": 446, "reserve_winner_id": 447, "winner_confirmation": "2", "license": null, "status": "5", "personal_account": null, "created_at": "2021-07-27 02:43:44", "updated_at": "2021-08-11 19:21:07", "winner_doc_id": 21424, "required_percent": "1", "checking_account": "22604000900672547001 \u041c\u0424\u041e -00111", "comission_1_checked_date": null, "moderator_checked_date": "2021-07-27 09:24:57", "send_to_commission_at": null, "updated": null, "modified_by": 1902, "finance_moderator_checked_date": "2021-07-27 13:52:04", "placement_term_left": null, "reason_of_deletion_file": null, "transaction_date": "2021-08-11 19:21:07", "customer_fio": null, "show_scores": null, "rejected_offeror_id": null, "t_moderator_date": "2021-07-27 02:48:29", "failed_reason": null, "t_customer_confirmed": null, "t_confirmed_date": null, "old_tender_id": null, "customer_position": null, "customer_address": null, "prikaz": null, "bidders_count": 2, "customer_info": {"id": 324, "name": "\u0413\u0423\u041f BUXOROSUVQURILISHINVEST", "organisation_director": "\u041a\u0410\u0414\u0418\u0420\u041e\u0412 \u041e\u041b\u0418\u041c \u0417\u0410\u0418\u0420\u041e\u0412\u0418\u0427"}, "region": {"id": 2, "name": "\u0411\u0443\u0445\u0430\u0440\u0441\u043a\u0430\u044f \u043e\u0431\u043b\u0430\u0441\u0442\u044c", "created_at": "2020-12-07T05:48:11.000000Z", "updated_at": "2020-12-07T05:48:11.000000Z", "deleted_at": null}}, {"id": 4006, "name": "\u0421\u0443\u0440\u0445\u043e\u043d\u0434\u0430\u0440\u0451 \u0432\u0438\u043b\u043e\u044f\u0442 \u041e\u043b\u0442\u0438\u043d\u0441\u043e\u0439 \u0442\u0443\u043c\u0430\u043d\u0438\u0434\u0430\u0433\u0438 \"\u0421\u0443\u0444\u0438 \u041e\u043b\u043b\u043e\u0451\u0440\" \u043c\u0430\u043a\u0431\u0430\u0440\u0430\u0441\u0438 \u0445\u0443\u0434\u0443\u0434\u0438\u043d\u0438 \u043e\u0431\u043e\u0434\u043e\u043d\u043b\u0430\u0448\u0442\u0438\u0440\u0438\u0448, \u043c\u0435\u0442\u0430\u043b\u043b \u0434\u0430\u0440\u0432\u043e\u0437\u0430 \u0432\u0430 \u0439\u0443\u043b \u0431\u0435\u043b\u0433\u0438\u043b\u0430\u0440\u0438 \u0443\u0440\u043d\u0430\u0442\u0438\u0448", "object_type_id": 2, "service_type_id": 3, "complexity_category_id": 2, "category_score_id": 8, "start_price": 838488662, "end_term_work": "2021-10-27", "end_term_work_days": 90, "region_id": 9, "district_id": 94, "address": "\u041e\u043b\u0442\u0438\u043d\u0441\u043e\u0439 \u0442\u0443\u043c\u0430\u043d\u0438", "phone": "(76) 223-44-78", "financial_source": "\u0411\u044e\u0434\u0436\u0435\u0442", "currency": "UZS", "language": null, "placement_term": "2021-08-12 23:59:59", "placement_term_days": 10, "contact_person": {"position": "akbar77077@mail.ru", "full_name": "\u0421\u0430\u0444\u0430\u0440\u043e\u0432 \u0424\u0430\u0440\u0440\u0443\u0445"}, "additional_information": "\u0422\u0435\u043d\u0434\u0435\u0440 \u0441\u0430\u0432\u0434\u043e\u043b\u0430\u0440\u0438\u0434\u0430 \u0438\u0448\u0442\u0438\u0440\u043e\u043a \u044d\u0442\u0438\u0448 \u0431\u0443\u044e\u0440\u0442\u043c\u0430\u0441\u0438\u043d\u0438 \u0442\u0430\u044a\u043c\u0438\u043d\u043b\u0430\u0448 \u0448\u0430\u043a\u043b\u0438 \u0431\u0430\u043d\u043a \u043a\u0430\u0444\u043e\u043b\u0430\u0442\u0438 \u0442\u0430\u0440\u0442\u0438\u0431\u0438\u0434\u0430 \u0451\u043a\u0438 \u043e\u0431\u044a\u0435\u043a\u0442\u043d\u0438\u043d\u0433 0,2%\u043c\u0438\u049b\u0434\u043e\u0440\u0438\u0434\u0430\u0433\u0438 \u0441\u0443\u043c\u043c\u0430\u043d\u0438 \u0444\u0430\u049b\u0430\u0442 \u0431\u0443\u044e\u0440\u0442\u043c\u0430\u0447\u0438\u043d\u0438\u043d\u0433 \u043c\u0430\u0445\u0441\u0443\u0441 \u04b3\u0438\u0441\u043e\u0431 \u0440\u0430\u049b\u0430\u043c\u0438\u0433\u0430 \u045e\u0442\u043a\u0430\u0437\u0438\u0448 \u0432\u0430 \u0442\u045e\u043b\u0430\u043d\u0433\u0430\u043d\u043b\u0438\u043a \u0442\u045e\u0493\u0440\u0438\u0441\u0438\u0434\u0430\u0433\u0438 \u0442\u045e\u043b\u043e\u0432 \u0442\u043e\u043f\u0448\u0438\u0440\u0438\u049b\u043d\u043e\u043c\u0430\u0441\u0438 \u043d\u0443\u0441\u0445\u0430\u0441\u0438\u043d\u0438 \u0442\u0430\u049b\u0434\u0438\u043c \u044d\u0442\u0438\u0448.\u0422\u045e\u043b\u043e\u0432 \u0444\u0430\u049b\u0430\u0442 \u0430\u0441\u043e\u0441\u0438\u0439 \u0445\u0438\u0441\u043e\u0431 \u0440\u0430\u049b\u0430\u043c\u0434\u0430\u043d \u045e\u0442\u043a\u0430\u0437\u0438\u043b\u0438\u0448\u0438 \u0448\u0430\u0440\u0442. \u0411\u0443\u044e\u0440\u0442\u043c\u0430\u0447\u0438 \u0445\u0438\u0441\u043e\u0431 \u0440\u0430\u049b\u0430\u043c\u0438: \u0425/\u0420: 22626000800312084755,  \u041c\u0424\u041e: 00356,  \u0418\u041d\u041d: 200474347. \u0410\u0439\u043b\u0430\u043d\u043c\u0430 \u043c\u0430\u0431\u043b\u0430\u0493\u043b\u0430\u0440 \u043e\u0431\u044a\u0435\u043a\u0442 \u0431\u043e\u0448\u043b\u0430\u043d\u0493\u0438\u0447 \u043d\u0430\u0440\u0445\u0438\u043d\u0438\u043d\u0433 20% \u0434\u0430\u043d \u043a\u0430\u043c \u043c\u0438\u049b\u0434\u043e\u0440\u0438\u043d\u0438 \u0442\u0430\u0448\u043a\u0438\u043b \u044d\u0442\u0433\u0430\u043d \u04b3\u043e\u043b\u043b\u0430\u0440\u0434\u0430, \u0438\u0448\u0442\u0438\u0440\u043e\u043a\u0447\u0438 \u0430\u0439\u043b\u0430\u043d\u043c\u0430 \u043c\u0430\u0431\u043b\u0430\u0493\u043b\u0430\u0440\u0438 \u043c\u0430\u0432\u0436\u0443\u0434\u043b\u0438\u0433\u0438 \u04b3\u0430\u049b\u0438\u0434\u0430\u0433\u0438 \u0431\u0430\u043d\u043a \u0442\u0430\u0441\u0434\u0438\u049b\u043b\u0430\u0433\u0430\u043d \u043c\u0430\u044a\u043b\u0443\u043c\u043e\u0442\u043d\u043e\u043c\u0430\u043d\u0438 \u0432\u0430 \u0435\u0442\u043c\u0430\u0451\u0442\u0433\u0430\u043d \u0441\u0443\u043c\u043c\u0430\u0433\u0430 \u0431\u0430\u043d\u043a \u043a\u0430\u0444\u0438\u043b\u043b\u0438\u0433\u0438\u043d\u0438 \u0442\u0430\u049b\u0434\u0438\u043c \u044d\u0442\u0430\u0434\u0438 (20 \u0444\u043e\u0438\u0437)", "contract": "contracts/contract-4006.doc", "unique_name": 13928, "psd": "psd/\u043f\u0441\u0434-4006.zip", "expertise": "expertise/expertise-4006.PDF", "reason_of_deletion": null, "protocol": "pdf/protocol-4006.pdf", "customer_id": 76, "consulting_id": 53, "request_id": 3417, "winner_id": null, "reserve_winner_id": null, "winner_confirmation": null, "license": null, "status": "29", "personal_account": null, "created_at": "2021-07-26 17:57:49", "updated_at": "2021-08-17 10:26:41", "winner_doc_id": null, "required_percent": "0.2", "checking_account": "\"\u0425/\u0420: 22626000800312084755,  \u041c\u0424\u041e: 00356,  \u0418\u041d\u041d: 200474347. \"", "comission_1_checked_date": null, "moderator_checked_date": "2021-07-27 09:23:34", "send_to_commission_at": null, "updated": null, "modified_by": 1902, "finance_moderator_checked_date": "2021-07-28 19:21:07", "placement_term_left": null, "reason_of_deletion_file": null, "transaction_date": "2021-08-17 10:26:41", "customer_fio": null, "show_scores": null, "rejected_offeror_id": null, "t_moderator_date": "2021-07-26 18:04:28", "failed_reason": null, "t_customer_confirmed": null, "t_confirmed_date": null, "old_tender_id": null, "customer_position": null, "customer_address": null, "prikaz": null, "bidders_count": 4, "customer_info": {"id": 76, "name": "\u042f\u0413\u041e\u041d\u0410 \u0411\u0423\u042e\u0420\u0422\u041c\u0410\u0427\u0418 \u0425\u0418\u0417\u041c\u0410\u0422\u0418 \u0418\u041d\u0416\u0418\u041d\u0418\u0420\u0418\u041d\u0413 \u041a\u041e\u041c\u041f\u0410\u041d\u0418\u042f\u0421\u0418", "organisation_director": "\u0410\u0420\u0410\u041c\u041e\u0412 \u0410\u0421\u041b\u0418\u0414\u0414\u0418\u041d \u0425\u041e\u0428\u0418\u041c\u041e\u0412\u0418\u0427"}, "region": {"id": 9, "name": "\u0421\u0443\u0440\u0445\u0430\u043d\u0434\u0430\u0440\u044c\u0438\u043d\u0441\u043a\u0430\u044f \u043e\u0431\u043b\u0430\u0441\u0442\u044c", "created_at": "2020-12-07T05:59:49.000000Z", "updated_at": "2020-12-07T05:59:49.000000Z", "deleted_at": null}}, {"id": 4005, "name": "\u0424\u0430\u0440\u0493\u043e\u043d\u0430 \u0432\u0438\u043b\u043e\u044f\u0442\u0438 \u0401\u0437\u0451\u0432\u043e\u043d \u0442\u0443\u043c\u0430\u043d\u0438 \u0422\u043e\u0448\u0445\u043e\u0432\u0443\u0437 \u041c\u0424\u0419\u0434\u0430 90 \u045e\u0440\u0438\u043d\u043b\u0438 \u044f\u043d\u0433\u0438 \u043c\u0430\u043a\u0442\u0430\u0431\u0433\u0430\u0447\u0430 \u0442\u0430\u044a\u043b\u0438\u043c \u043c\u0443\u0430\u0441\u0441\u0430\u0441\u0430\u0441\u0438 (\u041c\u0422\u041c) \u049b\u0443\u0440\u0438\u0448", "object_type_id": 2, "service_type_id": 3, "complexity_category_id": 2, "category_score_id": 8, "start_price": 3039301135, "end_term_work": "2021-12-24", "end_term_work_days": 150, "region_id": 11, "district_id": 137, "address": "\u0401\u0437\u0451\u0432\u043e\u043d \u0442\u0443\u043c\u0430\u043d\u0438", "phone": "(99) 615-68-91", "financial_source": "\u0420\u0435\u0441\u043f\u0443\u0431\u043b\u0438\u043a\u0430 \u0431\u044e\u0434\u0436\u0435\u0442\u0438 \u043c\u0430\u0431\u043b\u0430\u0493\u043b\u0430\u0440\u0438", "currency": "UZS", "language": null, "placement_term": "2021-08-10 23:59:59", "placement_term_days": 10, "contact_person": {"position": "fartender@mail.ru", "full_name": "\u041a\u0430\u0440\u0432\u043e\u043d\u043e\u0432 \u0412\u043e\u04b3\u0438\u0434\u0436\u043e\u043d"}, "additional_information": "\u0422\u0430\u043d\u043b\u043e\u0432 \u0441\u0430\u0432\u0434\u043e\u043b\u0430\u0440\u0438\u0434\u0430 \u0438\u0448\u0442\u0438\u0440\u043e\u043a \u044d\u0442\u0438\u0448 \u0431\u0443\u044e\u0440\u0442\u043c\u0430\u0441\u0438\u043d\u0438 \u0442\u0430\u044a\u043c\u0438\u043d\u043b\u0430\u0448 \u0448\u0430\u043a\u043b\u0438 \u0431\u0430\u043d\u043a \u043a\u0430\u0444\u043e\u043b\u0430\u0442\u0438 \u0442\u0430\u0440\u0442\u0438\u0431\u0438\u0434\u0430 \u0451\u043a\u0438 \u043e\u0431\u044a\u0435\u043a\u0442\u043d\u0438\u043d\u0433 1% \u043c\u0438\u049b\u0434\u043e\u0440\u0438\u0434\u0430\u0433\u0438 \u0441\u0443\u043c\u043c\u0430\u043d\u0438 \u0444\u0430\u049b\u0430\u0442 \u0431\u0443\u044e\u0440\u0442\u043c\u0430\u0447\u0438\u043d\u0438\u043d\u0433 \u043c\u0430\u0445\u0441\u0443\u0441 \u04b3\u0438\u0441\u043e\u0431 \u0440\u0430\u049b\u0430\u043c\u0438\u0433\u0430 \u045e\u0442\u043a\u0430\u0437\u0438\u0448 \u0432\u0430 \u0442\u045e\u043b\u0430\u043d\u0433\u0430\u043d\u043b\u0438\u043a \u0442\u045e\u0493\u0440\u0438\u0441\u0438\u0434\u0430\u0433\u0438 \u0442\u045e\u043b\u043e\u0432 \u0442\u043e\u043f\u0448\u0438\u0440\u0438\u049b\u043d\u043e\u043c\u0430\u0441\u0438 \u043d\u0443\u0441\u0445\u0430\u0441\u0438\u043d\u0438 \u0442\u0430\u049b\u0434\u0438\u043c \u044d\u0442\u0438\u0448. \u0411\u0443\u044e\u0440\u0442\u043c\u0430\u0447\u0438 \u0445\u0438\u0441\u043e\u0431 \u0440\u0430\u049b\u0430\u043c\u0438: \u041e\u0410\u041a\u0411 \u201c\u041a\u0430\u043f\u0438\u0442\u0430\u043b\u0431\u0430\u043d\u043a\u201d \u0424\u0430\u0440\u0433\u043e\u043d\u0430 \u0444\u0438\u043b\u0438\u0430\u043b\u0438, \u0425/\u0440: 22604000700210242002; \u041c\u0424\u041e: 01043 \u0418\u041d\u041d: 204816336. \u0410\u0439\u043b\u0430\u043d\u043c\u0430 \u043c\u0430\u0431\u043b\u0430\u0493\u043b\u0430\u0440 \u043e\u0431\u044a\u0435\u043a\u0442 \u0431\u043e\u0448\u043b\u0430\u043d\u0493\u0438\u0447 \u043d\u0430\u0440\u0445\u0438\u043d\u0438\u043d\u0433 20% \u0434\u0430\u043d \u043a\u0430\u043c \u043c\u0438\u049b\u0434\u043e\u0440\u0438\u043d\u0438 \u0442\u0430\u0448\u043a\u0438\u043b \u044d\u0442\u0433\u0430\u043d \u04b3\u043e\u043b\u043b\u0430\u0440\u0434\u0430, \u0438\u0448\u0442\u0438\u0440\u043e\u043a\u0447\u0438 \u0430\u0439\u043b\u0430\u043d\u043c\u0430 \u043c\u0430\u0431\u043b\u0430\u0493\u043b\u0430\u0440\u0438 \u043c\u0430\u0432\u0436\u0443\u0434\u043b\u0438\u0433\u0438 \u04b3\u0430\u049b\u0438\u0434\u0430\u0433\u0438 \u0431\u0430\u043d\u043a \u0442\u0430\u0441\u0434\u0438\u049b\u043b\u0430\u0433\u0430\u043d \u043c\u0430\u044a\u043b\u0443\u043c\u043e\u0442\u043d\u043e\u043c\u0430\u043d\u0438 \u0451\u043a\u0438 \u0435\u0442\u043c\u0430\u0451\u0442\u0433\u0430\u043d \u0441\u0443\u043c\u043c\u0430\u0433\u0430 \u0431\u0430\u043d\u043a \u043a\u0430\u0444\u0438\u043b\u043b\u0438\u0433\u0438\u043d\u0438 \u0442\u0430\u049b\u0434\u0438\u043c \u044d\u0442\u0430\u0434\u0438 (20 \u0444\u043e\u0438\u0437)", "contract": "contracts/contract-4005.doc", "unique_name": 13927, "psd": "psd/\u043f\u0441\u0434-4005.pdf", "expertise": "expertise/expertise-4005.pdf", "reason_of_deletion": null, "protocol": "pdf/protocol-4005.pdf", "customer_id": 66, "consulting_id": 56, "request_id": 3406, "winner_id": 315, "reserve_winner_id": 453, "winner_confirmation": "2", "license": null, "status": "5", "personal_account": null, "created_at": "2021-07-26 17:30:54", "updated_at": "2021-08-13 19:39:06", "winner_doc_id": 21233, "required_percent": "1", "checking_account": "\u0425/\u0440: 22604000700210242002; \u041c\u0424\u041e: 01043 \u0418\u041d\u041d: 204816336", "comission_1_checked_date": null, "moderator_checked_date": "2021-07-27 11:01:38", "send_to_commission_at": null, "updated": null, "modified_by": 1902, "finance_moderator_checked_date": "2021-07-27 13:52:19", "placement_term_left": null, "reason_of_deletion_file": null, "transaction_date": "2021-08-13 19:39:06", "customer_fio": null, "show_scores": null, "rejected_offeror_id": null, "t_moderator_date": "2021-07-27 09:43:50", "failed_reason": null, "t_customer_confirmed": null, "t_confirmed_date": null, "old_tender_id": null, "customer_position": null, "customer_address": null, "prikaz": null, "bidders_count": 6, "customer_info": {"id": 66, "name": "\u042f\u0413\u041e\u041d\u0410 \u0411\u0423\u042e\u0420\u0422\u041c\u0410\u0427\u0418 \u0425\u0418\u0417\u041c\u0410\u0422\u0418-\u0418\u041d\u0416\u0418\u041d\u0418", "organisation_director": "\u0410\u0411\u0414\u0423\u041a\u0410\u0420\u0418\u041c\u041e\u0412 \u0414\u0418\u041b\u0428\u041e\u0414 \u0422\u0423\u0425\u0422\u0410\u0421\u0418\u041d\u041e\u0412\u0418\u0427"}, "region": {"id": 11, "name": "\u0424\u0435\u0440\u0433\u0430\u043d\u0441\u043a\u0430\u044f \u043e\u0431\u043b\u0430\u0441\u0442\u044c", "created_at": "2020-12-07T06:04:42.000000Z", "updated_at": "2020-12-07T06:04:42.000000Z", "deleted_at": null}}, {"id": 4004, "name": "\u0421\u0442\u0440\u043e\u0438\u0442\u0435\u043b\u044c\u0441\u0442\u0432\u043e \u0441\u0438\u0441\u0442\u0435\u043c\u044b \u0438\u0440\u0440\u0438\u0433\u0430\u0446\u0438\u0438-\u043c\u0435\u043b\u0438\u043e\u0440\u0430\u0446\u0438\u0438 \u0432 \u0446\u0435\u043b\u044f\u0445 \u0438\u0441\u043f\u043e\u043b\u044c\u0437\u043e\u0432\u0430\u043d\u0438\u0435 \u043e\u0431\u043e\u0440\u043e\u0442\u043e\u043c \u0437\u0435\u043c\u043b\u0438 \"\u0412\u043e\u0445\u0438\u0434\u0431\u0435\u043a \u0414\u0438\u0451\u0440\u0431\u0435\u043a \u0417\u0430\u043c\u0438\u043d\u0438\" \u0424/\u0425 \u043d\u0430 \u0442\u0435\u0440\u0440\u0438\u0442\u043e\u0440\u0438\u0438 \"\u0428\u0443\u0440\u043e\u0431\u043e\u0434\" \u0432 \u041a\u0430\u0440\u0430\u043a\u0443\u043b\u0441\u043a\u043e\u043c \u0440\u0430\u0439\u043e\u043d\u0435 \u0411\u0443\u0445\u0430\u0440\u0441\u043a\u043e\u0439 \u043e\u0431\u043b\u0430\u0441\u0442\u0438", "object_type_id": 4, "service_type_id": 3, "complexity_category_id": 3, "category_score_id": 8, "start_price": 2406982025, "end_term_work": "2021-10-25", "end_term_work_days": 90, "region_id": 2, "district_id": 23, "address": "\u049a\u043e\u0440\u0430\u043a\u045e\u043b \u0442\u0443\u043c\u0430\u043d\u0438 \"\u0428\u045e\u0440\u043e\u0431\u043e\u0434\" \u04b3\u0443\u0434\u0443\u0434\u0438\u0434\u0430", "phone": "(91) 923-58-72", "financial_source": "\u0437\u0430 \u0441\u0447\u0451\u0442 \u0441\u0440\u0435\u0434\u0441\u0442\u0432 \u043c\u0435\u0441\u0442\u043d\u043e\u0433\u043e \u0431\u044e\u0434\u0436\u0435\u0442\u0430", "currency": "UZS", "language": null, "placement_term": "2021-08-10 23:59:59", "placement_term_days": 10, "contact_person": {"position": "kafiyat79@mail.ru", "full_name": "\u0411\u043e\u0431\u043e\u0436\u043e\u043d\u043e\u0432 \u0410\u0437\u0438\u0437"}, "additional_information": "\"\u0422\u0430\u043d\u043b\u043e\u0432 \u0441\u0430\u0432\u0434\u043e\u043b\u0430\u0440\u0438\u0434\u0430 \u0438\u0448\u0442\u0438\u0440\u043e\u043a \u044d\u0442\u0438\u0448 \u0431\u0443\u044e\u0440\u0442\u043c\u0430\u0441\u0438\u043d\u0438 \u0442\u0430\u044a\u043c\u0438\u043d\u043b\u0430\u0448 \u0448\u0430\u043a\u043b\u0438 \u0431\u0430\u043d\u043a \u043a\u0430\u0444\u043e\u043b\u0430\u0442\u0438 \u0442\u0430\u0440\u0442\u0438\u0431\u0438\u0434\u0430 \u0451\u043a\u0438 \u043e\u0431\u044a\u0435\u043a\u0442\u043d\u0438\u043d\u0433 1% \u043c\u0438\u049b\u0434\u043e\u0440\u0438\u0434\u0430\u0433\u0438 \u0441\u0443\u043c\u043c\u0430\u043d\u0438 \u0444\u0430\u049b\u0430\u0442 \u0431\u0443\u044e\u0440\u0442\u043c\u0430\u0447\u0438\u043d\u0438\u043d\u0433 \u043c\u0430\u0445\u0441\u0443\u0441 \u04b3\u0438\u0441\u043e\u0431 \u0440\u0430\u049b\u0430\u043c\u0438\u0433\u0430 \u045e\u0442\u043a\u0430\u0437\u0438\u0448 \u0432\u0430 \u0442\u045e\u043b\u0430\u043d\u0433\u0430\u043d\u043b\u0438\u043a \u0442\u045e\u0493\u0440\u0438\u0441\u0438\u0434\u0430\u0433\u0438 \u0442\u045e\u043b\u043e\u0432 \u0442\u043e\u043f\u0448\u0438\u0440\u0438\u049b\u043d\u043e\u043c\u0430\u0441\u0438 \u043d\u0443\u0441\u0445\u0430\u0441\u0438\u043d\u0438 \u0431\u0438\u0440\u0438\u043a\u0442\u0438\u0440\u0438\u043b\u0430\u0434\u0438. \u0411\u0443\u044e\u0440\u0442\u043c\u0430\u0447\u0438 \u0445\u0438\u0441\u043e\u0431 \u0440\u0430\u049b\u0430\u043c\u0438: \u0410\u0422\u0411 \u201c\u0422\u0443\u0440\u043e\u043d \u0431\u0430\u043d\u043a\u201d \u0411\u0443\u0445\u043e\u0440\u043e \u0444\u0438\u043b\u0438\u0430\u043b\u0438 \u0425/\u0440:22604000900672547001; \u041c\u0424\u041e:00111 \u0418\u041d\u041d: 203269804. \u0410\u0439\u043b\u0430\u043d\u043c\u0430 \u043c\u0430\u0431\u043b\u0430\u0493\u043b\u0430\u0440 \u043e\u0431\u044a\u0435\u043a\u0442 \u0431\u043e\u0448\u043b\u0430\u043d\u0493\u0438\u0447 \u043d\u0430\u0440\u0445\u0438\u043d\u0438\u043d\u0433 20% \u0434\u0430\u043d \u043a\u0430\u043c \u043c\u0438\u049b\u0434\u043e\u0440\u0438\u043d\u0438 \u0442\u0430\u0448\u043a\u0438\u043b \u044d\u0442\u0433\u0430\u043d \u04b3\u043e\u043b\u043b\u0430\u0440\u0434\u0430, \u0438\u0448\u0442\u0438\u0440\u043e\u043a\u0447\u0438 \u0430\u0439\u043b\u0430\u043d\u043c\u0430 \u043c\u0430\u0431\u043b\u0430\u0493\u043b\u0430\u0440\u0438 \u043c\u0430\u0432\u0436\u0443\u0434\u043b\u0438\u0433\u0438 \u04b3\u0430\u049b\u0438\u0434\u0430\u0433\u0438 \u0431\u0430\u043d\u043a \u0442\u0430\u0441\u0434\u0438\u049b\u043b\u0430\u0433\u0430\u043d \u043c\u0430\u044a\u043b\u0443\u043c\u043e\u0442\u043d\u043e\u043c\u0430\u043d\u0438 \u0432\u0430 \u0435\u0442\u043c\u0430\u0451\u0442\u0433\u0430\u043d \u0441\u0443\u043c\u043c\u0430\u0433\u0430 \u0431\u0430\u043d\u043a \u043a\u0430\u0444\u0438\u043b\u043b\u0438\u0433\u0438\u043d\u0438 \u0431\u0438\u0440\u0438\u043a\u0442\u0438\u0440\u0430\u0434\u0438 (20 \u0444\u043e\u0438\u0437).\n\u041e\u0431\u044a\u0435\u043a\u0442\u0434\u0430 \u0438\u0445\u0442\u0438\u0441\u043e\u0441\u043b\u0430\u0448\u0442\u0438\u0440\u0438\u043b\u0433\u0430\u043d \u0442\u0430\u0448\u043a\u0438\u043b\u043e\u0442\u043b\u0430\u0440 \u049b\u0430\u0442\u043d\u0430\u0448\u0438\u0448\u043b\u0430\u0440\u0438 \u0442\u0430\u043b\u0430\u0431 \u049b\u0438\u043b\u0438\u043d\u0430\u0434\u0438.\"", "contract": "contracts/contract-4004.doc", "unique_name": 13926, "psd": "psd/\u043f\u0441\u0434-4004.rar", "expertise": "expertise/expertise-4004.pdf", "reason_of_deletion": "\u0418\u043a\u043a\u0430\u043b\u0430 \u0442\u0430\u043b\u0430\u0431\u0433\u043e\u0440\u043b\u0430\u0440 \u0442\u043e\u043c\u043e\u043d\u0438\u0434\u0430\u043d \u043f\u043b\u0430\u0442\u0444\u043e\u0440\u043c\u0430\u0434\u0430 \u044e\u043a\u043b\u0430\u043d\u0433\u0430\u043d \u04b3\u0443\u0436\u0436\u0430\u0442\u043b\u0430\u0440 \u043a\u0435\u043b\u0438\u0448\u0438\u043b\u0433\u0430\u043d \u0445\u043e\u043b\u0434\u0430, \u044f\u044a\u043d\u0438 2 \u0442\u0430\u043b\u0430\u0431\u0433\u043e\u0440\u0433\u0430 \u0445\u0430\u043c \u0431\u0438\u0442\u0442\u0430 \u0442\u0430\u043b\u0431\u0433\u043e\u0440\u043d\u0438\u043d\u0433 \u0431\u0430\u043d\u043a \u043a\u0430\u0444\u0438\u043b\u043b\u0438\u0433\u0438 \u0432\u0430 \u043c\u0430\u044a\u043b\u0443\u043c\u043e\u0442\u043d\u043e\u043c\u0430\u0441\u0438 \u0445\u0430\u043c\u0434\u0430 \u0438\u0448 \u0445\u0430\u0436\u043c\u043b\u0430\u0440\u0438 \u0442\u0443\u0433\u0440\u0438\u0441\u0438\u0434\u0430\u0433\u0438 \u0439\u0438\u0433\u043c\u0430 \u0436\u0430\u043c\u043b\u0430\u043d\u043c\u0430, \u043b\u043e\u043a\u0430\u043b\u044c \u043a\u0430\u0439\u0434\u043d\u043e\u043c\u0430, \u0430\u0441\u043e\u0441\u0438\u0439 \u043d\u0430\u0440\u0445 \u0448\u0430\u043a\u043b\u043b\u0430\u043d\u0442\u0438\u0440\u0443\u0432\u0447\u0438 \u043a\u043e\u043c\u043f\u043e\u043d\u0435\u043d\u0442\u043b\u0430\u0440 \u0431\u0438\u0440 \u0445\u0438\u043b \u0442\u0430\u0439\u0451\u0440\u043b\u0430\u0431 \u044e\u043a\u043b\u0430\u043d\u0433\u0430\u043d.", "protocol": null, "customer_id": 324, "consulting_id": 3007, "request_id": 3415, "winner_id": 3416, "reserve_winner_id": 1161, "winner_confirmation": null, "license": null, "status": "32", "personal_account": null, "created_at": "2021-07-26 17:22:25", "updated_at": "2021-08-14 16:14:43", "winner_doc_id": 21491, "required_percent": "1", "checking_account": "22604000900672547001 \u041c\u0424\u041e -00111", "comission_1_checked_date": null, "moderator_checked_date": "2021-07-26 17:48:13", "send_to_commission_at": null, "updated": null, "modified_by": 1907, "finance_moderator_checked_date": "2021-07-26 22:53:27", "placement_term_left": null, "reason_of_deletion_file": null, "transaction_date": null, "customer_fio": null, "show_scores": null, "rejected_offeror_id": null, "t_moderator_date": "2021-07-26 17:26:44", "failed_reason": null, "t_customer_confirmed": "2021-08-14 16:14:43", "t_confirmed_date": null, "old_tender_id": null, "customer_position": null, "customer_address": null, "prikaz": null, "bidders_count": 2, "customer_info": {"id": 324, "name": "\u0413\u0423\u041f BUXOROSUVQURILISHINVEST", "organisation_director": "\u041a\u0410\u0414\u0418\u0420\u041e\u0412 \u041e\u041b\u0418\u041c \u0417\u0410\u0418\u0420\u041e\u0412\u0418\u0427"}, "region": {"id": 2, "name": "\u0411\u0443\u0445\u0430\u0440\u0441\u043a\u0430\u044f \u043e\u0431\u043b\u0430\u0441\u0442\u044c", "created_at": "2020-12-07T05:48:11.000000Z", "updated_at": "2020-12-07T05:48:11.000000Z", "deleted_at": null}}, {"id": 4003, "name": "\u0422\u043e\u0448\u043a\u0435\u043d\u0442 \u0432\u0438\u043b\u043e\u044f\u0442\u0438 \u049a\u0443\u0439\u0438\u0447\u0438\u0440\u0447\u0438\u049b \u0442\u0443\u043c\u0430\u043d\u0438, \u0411\u0430\u0440\u043a\u0430\u043c\u043e\u043b \u0432\u0430 \u0411\u0438\u0431\u0438\u0445\u043e\u043d\u0438\u043c \u043a\u045e\u0447\u0430\u043b\u0430\u0440\u0438\u043d\u0438 \u043e\u0431\u043e\u0434\u043e\u043d\u043b\u0430\u0448\u0442\u0438\u0440\u0438\u0448 (\u0442\u0443\u043d\u0433\u0438 \u0451\u0440\u0438\u0442\u0438\u0448 \u0447\u0438\u0440\u043e\u049b\u043b\u0430\u0440\u0438\u043d\u0438 \u045e\u0440\u043d\u0430\u0442\u0438\u0448, \u043f\u0438\u0451\u0434\u0430\u043b\u0430\u0440 \u0432\u0430 \u0432\u0435\u043b\u043e\u0441\u0438\u043f\u0435\u0434 \u0439\u045e\u043b\u0430\u043a\u043b\u0430\u0440\u0438\u043d\u0438 \u049b\u0443\u0440\u0438\u0448)", "object_type_id": 2, "service_type_id": 3, "complexity_category_id": 2, "category_score_id": 8, "start_price": 4287087503, "end_term_work": "2021-11-03", "end_term_work_days": 100, "region_id": 10, "district_id": 115, "address": "\u0411\u0430\u0440\u043a\u0430\u043c\u043e\u043b \u0432\u0430 \u0411\u0438\u0431\u0438\u0445\u043e\u043d\u0438\u043c", "phone": "(71) 207-72-31", "financial_source": "\u0420\u0435\u0441\u043f\u0443\u0431\u043b\u0438\u043a\u0430 \u0431\u044e\u0434\u0436\u0435\u0442 \u0445\u0438\u0441\u043e\u0431\u0438\u0434\u0430\u043d", "currency": "UZS", "language": null, "placement_term": "2021-08-09 23:59:59", "placement_term_days": 10, "contact_person": {"position": "marketing_guks@mail.ru", "full_name": "\u0421.\u0410\u0431\u0434\u0443\u0440\u0430\u0445\u043c\u043e\u043d\u043e\u0432"}, "additional_information": "\u0422\u0435\u043d\u0434\u0435\u0440 \u0441\u0430\u0432\u0434\u043e\u043b\u0430\u0440\u0438\u0434\u0430 \u0438\u0448\u0442\u0438\u0440\u043e\u043a \u044d\u0442\u0438\u0448 \u0431\u0443\u044e\u0440\u0442\u043c\u0430\u0441\u0438\u043d\u0438 \u0442\u0430\u044a\u043c\u0438\u043d\u043b\u0430\u0448 \u0448\u0430\u043a\u043b\u0438 \u0431\u0430\u043d\u043a \u043a\u0430\u0444\u043e\u043b\u0430\u0442\u0438 \u0442\u0430\u0440\u0442\u0438\u0431\u0438\u0434\u0430 \u0451\u043a\u0438 \u043e\u0431\u044a\u0435\u043a\u0442\u043d\u0438\u043d\u0433 0.5% \u043c\u0438\u049b\u0434\u043e\u0440\u0438\u0434\u0430\u0433\u0438 \u0441\u0443\u043c\u043c\u0430\u043d\u0438 \u0444\u0430\u049b\u0430\u0442 \u0431\u0443\u044e\u0440\u0442\u043c\u0430\u0447\u0438\u043d\u0438\u043d\u0433 \u043c\u0430\u0445\u0441\u0443\u0441 \u04b3\u0438\u0441\u043e\u0431 \u0440\u0430\u049b\u0430\u043c\u0438\u0433\u0430 \u045e\u0442\u043a\u0430\u0437\u0438\u0448 \u0432\u0430 \u0442\u045e\u043b\u0430\u043d\u0433\u0430\u043d\u043b\u0438\u043a \u0442\u045e\u0493\u0440\u0438\u0441\u0438\u0434\u0430\u0433\u0438 \u0442\u045e\u043b\u043e\u0432 \u0442\u043e\u043f\u0448\u0438\u0440\u0438\u049b\u043d\u043e\u043c\u0430\u0441\u0438 \u043d\u0443\u0441\u0445\u0430\u0441\u0438\u043d\u0438 \u0442\u0430\u049b\u0434\u0438\u043c \u044d\u0442\u0438\u0448. \u0422\u045e\u043b\u043e\u0432 \u0444\u0430\u049b\u0430\u0442 \u0430\u0441\u043e\u0441\u0438\u0439 \u0445\u0438\u0441\u043e\u0431 \u0440\u0430\u049b\u0430\u043c\u0434\u0430\u043d \u045e\u0442\u043a\u0430\u0437\u0438\u043b\u0438\u0448\u0438 \u0448\u0430\u0440\u0442. \u0411\u0443\u044e\u0440\u0442\u043c\u0430\u0447\u0438\u043d\u0438\u043d\u0433 \u0445\u0438\u0441\u043e\u0431-\u0440\u0430\u043a\u0430\u043c\u0438: \u0440/\u0441 2262 6000 3014 3645 8636; \u0410\u041a\u0418\u0411 \u0418\u043f\u043e\u0442\u0435\u043a\u0430 \u0411\u0430\u043d\u043a \u041c\u0435\u0445\u043d\u0430\u0442\u0441\u043a\u0438\u0439 \u0444-\u043b; \u041c\u0424\u041e 00423; (\u0418\u041d\u041d 202 230 110).\u0410\u0439\u043b\u0430\u043d\u043c\u0430 \u043c\u0430\u0431\u043b\u0430\u0493\u043b\u0430\u0440 \u043e\u0431\u044a\u0435\u043a\u0442 \u0431\u043e\u0448\u043b\u0430\u043d\u0493\u0438\u0447 \u043d\u0430\u0440\u0445\u0438\u043d\u0438\u043d\u0433 20% \u0434\u0430\u043d \u043a\u0430\u043c \u043c\u0438\u049b\u0434\u043e\u0440\u0438\u043d\u0438 \u0442\u0430\u0448\u043a\u0438\u043b \u044d\u0442\u0433\u0430\u043d \u04b3\u043e\u043b\u043b\u0430\u0440\u0434\u0430, \u0438\u0448\u0442\u0438\u0440\u043e\u043a\u0447\u0438 \u0430\u0439\u043b\u0430\u043d\u043c\u0430 \u043c\u0430\u0431\u043b\u0430\u0493\u043b\u0430\u0440\u0438 \u043c\u0430\u0432\u0436\u0443\u0434\u043b\u0438\u0433\u0438 \u04b3\u0430\u049b\u0438\u0434\u0430\u0433\u0438 \u0431\u0430\u043d\u043a \u0442\u0430\u0441\u0434\u0438\u049b\u043b\u0430\u0433\u0430\u043d \u043c\u0430\u044a\u043b\u0443\u043c\u043e\u0442\u043d\u043e\u043c\u0430\u043d\u0438 \u0432\u0430 \u0435\u0442\u043c\u0430\u0451\u0442\u0433\u0430\u043d \u0441\u0443\u043c\u043c\u0430\u0433\u0430 \u0431\u0430\u043d\u043a \u043a\u0430\u0444\u0438\u043b\u043b\u0438\u0433\u0438\u043d\u0438 \u0442\u0430\u049b\u0434\u0438\u043c \u044d\u0442\u0430\u0434\u0438 (20 \u0444\u043e\u0438\u0437)", "contract": "contracts/contract-4003.doc", "unique_name": 13925, "psd": "psd/\u043f\u0441\u0434-4003.rar", "expertise": "expertise/expertise-4003.pdf", "reason_of_deletion": null, "protocol": "pdf/protocol-4003.pdf", "customer_id": 75, "consulting_id": null, "request_id": null, "winner_id": 791, "reserve_winner_id": 2819, "winner_confirmation": "2", "license": null, "status": "5", "personal_account": "100021860274017049801018054", "created_at": "2021-07-26 16:42:41", "updated_at": "2021-08-14 19:02:31", "winner_doc_id": 21255, "required_percent": "0.5", "checking_account": "22626000301436458636; \u041c\u0424\u041e 00423; (\u0418\u041d\u041d 202 230 110)", "comission_1_checked_date": null, "moderator_checked_date": "2021-07-26 16:57:58", "send_to_commission_at": null, "updated": null, "modified_by": 1902, "finance_moderator_checked_date": "2021-07-26 17:48:51", "placement_term_left": null, "reason_of_deletion_file": null, "transaction_date": "2021-08-14 19:02:31", "customer_fio": null, "show_scores": null, "rejected_offeror_id": null, "t_moderator_date": "2021-07-26 16:45:57", "failed_reason": null, "t_customer_confirmed": null, "t_confirmed_date": null, "old_tender_id": null, "customer_position": null, "customer_address": null, "prikaz": null, "bidders_count": 7, "customer_info": {"id": 75, "name": "YAGONA  BUYURTMACI XIZMAT ING-", "organisation_director": "\u0420\u0410\u0425\u041c\u0410\u041d\u041e\u0412 \u0410\u0411\u0420\u041e\u0420\u0416\u041e\u041d \u0423\u041a\u0422\u0410\u041c\u041e\u0412\u0418\u0427"}, "region": {"id": 10, "name": "\u0422\u0430\u0448\u043a\u0435\u043d\u0442\u0441\u043a\u0430\u044f \u043e\u0431\u043b\u0430\u0441\u0442\u044c", "created_at": "2020-12-07T06:01:44.000000Z", "updated_at": "2020-12-07T06:01:44.000000Z", "deleted_at": null}}, {"id": 4002, "name": "\u0424\u0430\u0440\u0493\u043e\u043d\u0430 \u0432\u0438\u043b\u043e\u044f\u0442\u0438 \u0424\u0430\u0440\u0493\u043e\u043d\u0430 \u0442\u0443\u043c\u0430\u043d\u0438 \u042e\u049b\u043e\u0440\u0438 \u041c\u0438\u043d\u0434\u043e\u043d \u0413\u0443\u043b\u0448\u0430\u043d \u049b\u0438\u0448\u043b\u043e\u0493\u0438\u0434\u0430\u0433\u0438 1-\u0441\u043e\u043d\u043b\u0438 \u0448\u0438\u0444\u043e\u0445\u043e\u043d\u0430 \u0431\u0438\u043d\u043e \u0432\u0430 \u0438\u043d\u0448\u043e\u043e\u0442\u043b\u0430\u0440\u0438\u043d\u0438 \u0440\u0435\u043a\u043e\u043d\u0441\u0442\u0440\u0443\u043a\u0446\u0438\u044f \u049b\u0438\u043b\u0438\u0448", "object_type_id": 2, "service_type_id": 2, "complexity_category_id": 2, "category_score_id": 8, "start_price": 2599987967, "end_term_work": "2021-12-04", "end_term_work_days": 130, "region_id": 11, "district_id": 135, "address": "\u0424\u0430\u0440\u0493\u043e\u043d\u0430 \u0432\u0438\u043b\u043e\u044f\u0442\u0438 \u0424\u0430\u0440\u0493\u043e\u043d\u0430 \u0442\u0443\u043c\u0430\u043d\u0438", "phone": "(99) 615-68-91", "financial_source": "\u0420\u0435\u0441\u043f\u0443\u0431\u043b\u0438\u043a\u0430 \u0431\u044e\u0434\u0436\u0435\u0442\u0438 \u043c\u0430\u0431\u043b\u0430\u0493\u043b\u0430\u0440\u0438", "currency": "UZS", "language": null, "placement_term": "2021-08-10 23:59:59", "placement_term_days": 10, "contact_person": {"position": "fartender@mail.ru", "full_name": "\u041a\u0430\u0440\u0432\u043e\u043d\u043e\u0432 \u0412\u043e\u04b3\u0438\u0434\u0436\u043e\u043d"}, "additional_information": "\u0422\u0430\u043d\u043b\u043e\u0432 \u0441\u0430\u0432\u0434\u043e\u043b\u0430\u0440\u0438\u0434\u0430 \u0438\u0448\u0442\u0438\u0440\u043e\u043a \u044d\u0442\u0438\u0448 \u0431\u0443\u044e\u0440\u0442\u043c\u0430\u0441\u0438\u043d\u0438 \u0442\u0430\u044a\u043c\u0438\u043d\u043b\u0430\u0448 \u0448\u0430\u043a\u043b\u0438 \u0431\u0430\u043d\u043a \u043a\u0430\u0444\u043e\u043b\u0430\u0442\u0438 \u0442\u0430\u0440\u0442\u0438\u0431\u0438\u0434\u0430 \u0451\u043a\u0438 \u043e\u0431\u044a\u0435\u043a\u0442\u043d\u0438\u043d\u0433 1% \u043c\u0438\u049b\u0434\u043e\u0440\u0438\u0434\u0430\u0433\u0438 \u0441\u0443\u043c\u043c\u0430\u043d\u0438 \u0444\u0430\u049b\u0430\u0442 \u0431\u0443\u044e\u0440\u0442\u043c\u0430\u0447\u0438\u043d\u0438\u043d\u0433 \u043c\u0430\u0445\u0441\u0443\u0441 \u04b3\u0438\u0441\u043e\u0431 \u0440\u0430\u049b\u0430\u043c\u0438\u0433\u0430 \u045e\u0442\u043a\u0430\u0437\u0438\u0448 \u0432\u0430 \u0442\u045e\u043b\u0430\u043d\u0433\u0430\u043d\u043b\u0438\u043a \u0442\u045e\u0493\u0440\u0438\u0441\u0438\u0434\u0430\u0433\u0438 \u0442\u045e\u043b\u043e\u0432 \u0442\u043e\u043f\u0448\u0438\u0440\u0438\u049b\u043d\u043e\u043c\u0430\u0441\u0438 \u043d\u0443\u0441\u0445\u0430\u0441\u0438\u043d\u0438 \u0442\u0430\u049b\u0434\u0438\u043c \u044d\u0442\u0438\u0448. \u0411\u0443\u044e\u0440\u0442\u043c\u0430\u0447\u0438 \u0445\u0438\u0441\u043e\u0431 \u0440\u0430\u049b\u0430\u043c\u0438: \u041e\u0410\u041a\u0411 \u201c\u041a\u0430\u043f\u0438\u0442\u0430\u043b\u0431\u0430\u043d\u043a\u201d \u0424\u0430\u0440\u0433\u043e\u043d\u0430 \u0444\u0438\u043b\u0438\u0430\u043b\u0438, \u0425/\u0440: 22604000700210242002; \u041c\u0424\u041e: 01043 \u0418\u041d\u041d: 204816336. \u0410\u0439\u043b\u0430\u043d\u043c\u0430 \u043c\u0430\u0431\u043b\u0430\u0493\u043b\u0430\u0440 \u043e\u0431\u044a\u0435\u043a\u0442 \u0431\u043e\u0448\u043b\u0430\u043d\u0493\u0438\u0447 \u043d\u0430\u0440\u0445\u0438\u043d\u0438\u043d\u0433 20% \u0434\u0430\u043d \u043a\u0430\u043c \u043c\u0438\u049b\u0434\u043e\u0440\u0438\u043d\u0438 \u0442\u0430\u0448\u043a\u0438\u043b \u044d\u0442\u0433\u0430\u043d \u04b3\u043e\u043b\u043b\u0430\u0440\u0434\u0430, \u0438\u0448\u0442\u0438\u0440\u043e\u043a\u0447\u0438 \u0430\u0439\u043b\u0430\u043d\u043c\u0430 \u043c\u0430\u0431\u043b\u0430\u0493\u043b\u0430\u0440\u0438 \u043c\u0430\u0432\u0436\u0443\u0434\u043b\u0438\u0433\u0438 \u04b3\u0430\u049b\u0438\u0434\u0430\u0433\u0438 \u0431\u0430\u043d\u043a \u0442\u0430\u0441\u0434\u0438\u049b\u043b\u0430\u0433\u0430\u043d \u043c\u0430\u044a\u043b\u0443\u043c\u043e\u0442\u043d\u043e\u043c\u0430\u043d\u0438 \u0451\u043a\u0438 \u0435\u0442\u043c\u0430\u0451\u0442\u0433\u0430\u043d \u0441\u0443\u043c\u043c\u0430\u0433\u0430 \u0431\u0430\u043d\u043a \u043a\u0430\u0444\u0438\u043b\u043b\u0438\u0433\u0438\u043d\u0438 \u0442\u0430\u049b\u0434\u0438\u043c \u044d\u0442\u0430\u0434\u0438 (20 \u0444\u043e\u0438\u0437)", "contract": "contracts/contract-4002.doc", "unique_name": 13924, "psd": "psd/\u043f\u0441\u0434-4002.pdf", "expertise": "expertise/expertise-4002.pdf", "reason_of_deletion": null, "protocol": "pdf/protocol-4002.pdf", "customer_id": 66, "consulting_id": 56, "request_id": 3382, "winner_id": 1660, "reserve_winner_id": 4056, "winner_confirmation": "2", "license": null, "status": "5", "personal_account": null, "created_at": "2021-07-26 16:03:06", "updated_at": "2021-08-16 10:55:24", "winner_doc_id": 21507, "required_percent": "1", "checking_account": "\u0425/\u0440: 22604000700210242002; \u041c\u0424\u041e: 01043 \u0418\u041d\u041d: 204816336", "comission_1_checked_date": null, "moderator_checked_date": "2021-07-26 16:54:36", "send_to_commission_at": null, "updated": null, "modified_by": 1902, "finance_moderator_checked_date": "2021-07-26 17:54:34", "placement_term_left": null, "reason_of_deletion_file": null, "transaction_date": "2021-08-16 10:55:24", "customer_fio": null, "show_scores": null, "rejected_offeror_id": null, "t_moderator_date": "2021-07-26 16:08:34", "failed_reason": null, "t_customer_confirmed": null, "t_confirmed_date": null, "old_tender_id": null, "customer_position": null, "customer_address": null, "prikaz": null, "bidders_count": 8, "customer_info": {"id": 66, "name": "\u042f\u0413\u041e\u041d\u0410 \u0411\u0423\u042e\u0420\u0422\u041c\u0410\u0427\u0418 \u0425\u0418\u0417\u041c\u0410\u0422\u0418-\u0418\u041d\u0416\u0418\u041d\u0418", "organisation_director": "\u0410\u0411\u0414\u0423\u041a\u0410\u0420\u0418\u041c\u041e\u0412 \u0414\u0418\u041b\u0428\u041e\u0414 \u0422\u0423\u0425\u0422\u0410\u0421\u0418\u041d\u041e\u0412\u0418\u0427"}, "region": {"id": 11, "name": "\u0424\u0435\u0440\u0433\u0430\u043d\u0441\u043a\u0430\u044f \u043e\u0431\u043b\u0430\u0441\u0442\u044c", "created_at": "2020-12-07T06:04:42.000000Z", "updated_at": "2020-12-07T06:04:42.000000Z", "deleted_at": null}}, {"id": 4001, "name": "\u041a\u0430\u043f\u0438\u0442\u0430\u043b\u044c\u043d\u044b\u0439 \u0440\u0435\u043c\u043e\u043d\u0442 \u041a\u0430\u0440\u0430\u043a\u0430\u043b\u043f\u0430\u043a\u0441\u043a\u043e\u0433\u043e \u043d\u0430\u0443\u0447\u043d\u043e-\u0438\u0441\u0441\u043b\u0435\u0434\u043e\u0432\u0430\u0442\u0435\u043b\u044c\u0441\u043a\u043e\u0433\u043e \u0438\u043d\u0441\u0442\u0438\u0442\u0443\u0442\u0430 \u0435\u0441\u0442\u0435\u0441\u0442\u0432\u0435\u043d\u043d\u044b\u0445 \u043d\u0430\u0443\u043a", "object_type_id": 2, "service_type_id": 1, "complexity_category_id": 2, "category_score_id": 8, "start_price": 2750098730, "end_term_work": "2021-11-26", "end_term_work_days": 120, "region_id": 13, "district_id": 185, "address": "\u0443\u043b. \u0423\u0437\u0431\u0435\u043a\u0438\u0441\u0442\u0430\u043d \u0433\u0443\u0437\u0430\u0440\u0438, 41", "phone": "(71) 244-12-17", "financial_source": "\u0413\u043e\u0441\u0443\u0434\u0430\u0440\u0441\u0442\u0432\u0435\u043d\u043d\u044b\u0435 \u0431\u044e\u0434\u0436\u0435\u0442\u043d\u044b\u0435 \u0441\u0440\u0435\u0434\u0441\u0442\u0432\u0430", "currency": "UZS", "language": null, "placement_term": "2021-08-12 23:59:59", "placement_term_days": 10, "contact_person": {"position": "tender_tash@bk.ru", "full_name": "\u041d.\u0410\u0445\u043c\u0435\u0434\u043e\u0432"}, "additional_information": "null", "contract": "contracts/contract-4001.doc", "unique_name": 13923, "psd": "psd/\u043f\u0441\u0434-4001.rar", "expertise": "expertise/expertise-4001.pdf", "reason_of_deletion": null, "protocol": "pdf/protocol-4001.pdf", "customer_id": 6447, "consulting_id": 58, "request_id": 3405, "winner_id": null, "reserve_winner_id": null, "winner_confirmation": null, "license": null, "status": "29", "personal_account": null, "created_at": "2021-07-26 16:00:43", "updated_at": "2021-08-24 23:30:39", "winner_doc_id": null, "required_percent": "2", "checking_account": "\u0440/\u0441 \u0434\u043b\u044f \u043e\u0431\u0435\u0441\u043f\u0435\u0447\u0435\u043d\u0438\u044f \u0437\u0430\u044f\u0432\u043a\u0438 \u0432 \u0432\u0438\u0434\u0435 \u0437\u0430\u0434\u0430\u0442\u043a\u0430: 2021 0000 0005 1380 0001; \u0410\u041a\u0411 \u0423\u0437\u043f\u0440\u043e\u043c\u0441\u0442\u0440\u043e\u0439 \u0431\u0430\u043d\u043a \u0448\u0430\u04b3\u0430\u0440 \u043c\u0438\u043d\u0442\u0430\u049b\u0430\u0432\u0438\u0439 \u0444\u0438\u043b\u0438\u0430\u043b\u0438, \u041c\u0424\u041e 00424; \u0418\u041d\u041d 200555443", "comission_1_checked_date": null, "moderator_checked_date": "2021-07-29 09:45:51", "send_to_commission_at": null, "updated": null, "modified_by": 1907, "finance_moderator_checked_date": "2021-07-29 16:39:36", "placement_term_left": null, "reason_of_deletion_file": null, "transaction_date": "2021-08-24 23:30:39", "customer_fio": null, "show_scores": null, "rejected_offeror_id": null, "t_moderator_date": "2021-07-29 05:42:12", "failed_reason": null, "t_customer_confirmed": null, "t_confirmed_date": null, "old_tender_id": null, "customer_position": null, "customer_address": null, "prikaz": null, "bidders_count": 0, "customer_info": {"id": 6447, "name": "INKOM KAPITAL QURILISH DIK", "organisation_director": "\u041c\u0415\u041b\u0418\u041a\u0423\u0417\u0418\u0415\u0412 \u041c\u0410\u0425\u041c\u0423\u0414\u0416\u041e\u041d \u0425\u0425\u0425"}, "region": {"id": 13, "name": "\u0420\u0435\u0441\u043f\u0443\u0431\u043b\u0438\u043a\u0430 \u041a\u0430\u0440\u0430\u043a\u0430\u043b\u043f\u0430\u043a\u0441\u0442\u0430\u043d", "created_at": "2020-12-07T06:09:56.000000Z", "updated_at": "2020-12-07T06:09:56.000000Z", "deleted_at": null}}], "first_page_url": "http://tender.mc.uz/apis/api/v1/tenders?page=1", "from": 2151, "last_page": 570, "last_page_url": "http://tender.mc.uz/apis/api/v1/tenders?page=570", "next_page_url": "http://tender.mc.uz/apis/api/v1/tenders?page=217", "path": "http://tender.mc.uz/apis/api/v1/tenders", "per_page": 10, "prev_page_url": "http://tender.mc.uz/apis/api/v1/tenders?page=215", "to": 2160, "total": 5699}, "districts": [{"id": 1, "name": "\u0410\u043d\u0434\u0438\u0436\u0430\u043d", "region_id": 1, "created_at": null, "updated_at": null, "deleted_at": null}, {"id": 2, "name": "\u0410\u043b\u0442\u044b\u043d\u043a\u0443\u043b\u044c\u0441\u043a\u0438\u0439", "region_id": 1, "created_at": null, "updated_at": null, "deleted_at": null}, {"id": 3, "name": "\u0410\u0441\u0430\u043a\u0438\u043d\u0441\u043a\u0438\u0439", "region_id": 1, "created_at": null, "updated_at": null, "deleted_at": null}, {"id": 4, "name": "\u0411\u0430\u043b\u044b\u043a\u0447\u0438\u043d\u0441\u043a\u0438\u0439", "region_id": 1, "created_at": null, "updated_at": null, "deleted_at": null}, {"id": 5, "name": "\u0411\u0443\u0441\u0442\u0430\u043d", "region_id": 1, "created_at": null, "updated_at": null, "deleted_at": null}, {"id": 6, "name": "\u0411\u0443\u043b\u0430\u043a\u0431\u0430\u0448\u0438\u043d\u0441\u043a\u0438\u0439", "region_id": 1, "created_at": null, "updated_at": null, "deleted_at": null}, {"id": 8, "name": "\u0414\u0436\u0430\u043b\u0430\u043a\u0443\u0434\u0443\u043a\u0441\u043a\u0438\u0439", "region_id": 1, "created_at": null, "updated_at": null, "deleted_at": null}, {"id": 9, "name": "\u0418\u0437\u0431\u0430\u0441\u043a\u0430\u043d\u0441\u043a\u0438\u0439", "region_id": 1, "created_at": null, "updated_at": null, "deleted_at": null}, {"id": 11, "name": "\u041a\u0443\u0440\u0433\u0430\u043d\u0442\u0435\u043f\u0438\u043d\u0441\u043a\u0438\u0439", "region_id": 1, "created_at": null, "updated_at": null, "deleted_at": null}, {"id": 12, "name": "\u041c\u0430\u0440\u0445\u0430\u043c\u0430\u0442\u0441\u043a\u0438\u0439", "region_id": 1, "created_at": null, "updated_at": null, "deleted_at": null}, {"id": 13, "name": "\u041f\u0430\u0445\u0442\u0430\u0430\u0431\u0430\u0434\u0441\u043a\u0438\u0439", "region_id": 1, "created_at": null, "updated_at": null, "deleted_at": null}, {"id": 14, "name": "\u0423\u043b\u0443\u0433\u043d\u043e\u0440\u0441\u043a\u0438\u0439", "region_id": 1, "created_at": null, "updated_at": null, "deleted_at": null}, {"id": 15, "name": "\u0425\u043e\u0434\u0436\u0430\u0430\u0431\u0430\u0434\u0441\u043a\u0438\u0439", "region_id": 1, "created_at": null, "updated_at": null, "deleted_at": null}, {"id": 16, "name": "\u0428\u0430\u0445\u0440\u0438\u0445\u0430\u043d\u0441\u043a\u0438\u0439", "region_id": 1, "created_at": null, "updated_at": null, "deleted_at": null}, {"id": 17, "name": "\u0410\u043b\u0430\u0442\u0441\u043a\u0438\u0439", "region_id": 2, "created_at": null, "updated_at": null, "deleted_at": null}, {"id": 18, "name": "\u0411\u0443\u0445\u0430\u0440\u0441\u043a\u0438\u0439", "region_id": 2, "created_at": null, "updated_at": null, "deleted_at": null}, {"id": 19, "name": "\u0412\u0430\u0431\u043a\u0435\u043d\u0442\u0441\u043a\u0438\u0439", "region_id": 2, "created_at": null, "updated_at": null, "deleted_at": null}, {"id": 20, "name": "\u0413\u0438\u0436\u0434\u0443\u0432\u0430\u043d\u0441\u043a\u0438\u0439", "region_id": 2, "created_at": null, "updated_at": null, "deleted_at": null}, {"id": 21, "name": "\u0416\u043e\u043d\u0434\u043e\u0440\u0441\u043a\u0438\u0439", "region_id": 2, "created_at": null, "updated_at": null, "deleted_at": null}, {"id": 22, "name": "\u041a\u0430\u0433\u0430\u043d\u0441\u043a\u0438\u0439", "region_id": 2, "created_at": null, "updated_at": null, "deleted_at": null}, {"id": 23, "name": "\u041a\u0430\u0440\u0430\u043a\u0443\u043b\u044c\u0441\u043a\u0438\u0439", "region_id": 2, "created_at": null, "updated_at": null, "deleted_at": null}, {"id": 24, "name": "\u041a\u0430\u0440\u0430\u0443\u043b\u0431\u0430\u0437\u0430\u0440\u0441\u043a\u0438\u0439", "region_id": 2, "created_at": null, "updated_at": null, "deleted_at": null}, {"id": 25, "name": "\u041f\u0435\u0448\u043a\u0443\u043d\u0441\u043a\u0438\u0439", "region_id": 2, "created_at": null, "updated_at": null, "deleted_at": null}, {"id": 26, "name": "\u0420\u043e\u043c\u0438\u0442\u0430\u043d\u0441\u043a\u0438\u0439", "region_id": 2, "created_at": null, "updated_at": null, "deleted_at": null}, {"id": 27, "name": "\u0428\u0430\u0444\u0438\u0440\u043a\u0430\u043d\u0441\u043a\u0438\u0439", "region_id": 2, "created_at": null, "updated_at": null, "deleted_at": null}, {"id": 28, "name": "\u0410\u0440\u043d\u0430\u0441\u0430\u0439\u0441\u043a\u0438\u0439", "region_id": 3, "created_at": null, "updated_at": null, "deleted_at": null}, {"id": 29, "name": "\u0411\u0430\u0445\u043c\u0430\u043b\u044c\u0441\u043a\u0438\u0439", "region_id": 3, "created_at": null, "updated_at": null, "deleted_at": null}, {"id": 30, "name": "\u0413\u0430\u043b\u043b\u044f\u0430\u0440\u0430\u043b\u044c\u0441\u043a\u0438\u0439", "region_id": 3, "created_at": null, "updated_at": null, "deleted_at": null}, {"id": 31, "name": "\u0414\u0443\u0441\u0442\u043b\u0438\u043a\u0441\u043a\u0438\u0439", "region_id": 3, "created_at": null, "updated_at": null, "deleted_at": null}, {"id": 32, "name": "\u0417\u0430\u0430\u043c\u0438\u043d\u0441\u043a\u0438\u0439", "region_id": 3, "created_at": null, "updated_at": null, "deleted_at": null}, {"id": 33, "name": "\u0417\u0430\u0440\u0431\u0434\u0430\u0440\u0441\u043a\u0438\u0439", "region_id": 3, "created_at": null, "updated_at": null, "deleted_at": null}, {"id": 34, "name": "\u0417\u0430\u0444\u0430\u0440\u0430\u0431\u0430\u0434\u0441\u043a\u0438\u0439", "region_id": 3, "created_at": null, "updated_at": null, "deleted_at": null}, {"id": 35, "name": "\u041c\u0438\u0440\u0437\u0430\u0447\u0443\u043b\u044c\u0441\u043a\u0438\u0439", "region_id": 3, "created_at": null, "updated_at": null, "deleted_at": null}, {"id": 36, "name": "\u041f\u0430\u0445\u0442\u0430\u043a\u043e\u0440\u0441\u043a\u0438\u0439", "region_id": 3, "created_at": null, "updated_at": null, "deleted_at": null}, {"id": 37, "name": "\u0424\u0430\u0440\u0438\u0448\u0441\u043a\u0438\u0439", "region_id": 3, "created_at": null, "updated_at": null, "deleted_at": null}, {"id": 38, "name": "\u0428\u0430\u0440\u0430\u0444-\u0420\u0430\u0448\u0438\u0434\u043e\u0432\u0441\u043a\u0438\u0439 (\u0414\u0436\u0438\u0437\u0430\u043a\u0441\u043a\u0438\u0439)", "region_id": 3, "created_at": null, "updated_at": null, "deleted_at": null}, {"id": 39, "name": "\u042f\u043d\u0433\u0438\u0430\u0431\u0430\u0434\u0441\u043a\u0438\u0439", "region_id": 3, "created_at": null, "updated_at": null, "deleted_at": null}, {"id": 40, "name": "\u041a\u0430\u043d\u0438\u043c\u0435\u0445\u0441\u043a\u0438\u0439", "region_id": 4, "created_at": null, "updated_at": null, "deleted_at": null}, {"id": 41, "name": "\u041a\u0430\u0440\u043c\u0430\u043d\u0438\u043d\u0441\u043a\u0438\u0439", "region_id": 4, "created_at": null, "updated_at": null, "deleted_at": null}, {"id": 42, "name": "\u041a\u044b\u0437\u044b\u043b\u0442\u0435\u043f\u0438\u043d\u0441\u043a\u0438\u0439", "region_id": 4, "created_at": null, "updated_at": null, "deleted_at": null}, {"id": 43, "name": "\u041d\u0430\u0432\u0431\u0430\u0445\u043e\u0440\u0441\u043a\u0438\u0439", "region_id": 4, "created_at": null, "updated_at": null, "deleted_at": null}, {"id": 44, "name": "\u041d\u0443\u0440\u0430\u0442\u0438\u043d\u0441\u043a\u0438\u0439", "region_id": 4, "created_at": null, "updated_at": null, "deleted_at": null}, {"id": 45, "name": "\u0422\u0430\u043c\u0434\u044b\u043d\u0441\u043a\u0438\u0439", "region_id": 4, "created_at": null, "updated_at": null, "deleted_at": null}, {"id": 46, "name": "\u0423\u0447\u043a\u0443\u0434\u0443\u043a\u0441\u043a\u0438\u0439", "region_id": 4, "created_at": null, "updated_at": null, "deleted_at": null}, {"id": 47, "name": "\u0425\u0430\u0442\u044b\u0440\u0447\u0438\u043d\u0441\u043a\u0438\u0439", "region_id": 4, "created_at": null, "updated_at": null, "deleted_at": null}, {"id": 48, "name": "\u041a\u0430\u0441\u0430\u043d\u0441\u0430\u0439\u0441\u043a\u0438\u0439", "region_id": 5, "created_at": null, "updated_at": null, "deleted_at": null}, {"id": 49, "name": "\u041c\u0438\u043d\u0433\u0431\u0443\u043b\u0430\u043a\u0441\u043a\u0438\u0439", "region_id": 5, "created_at": null, "updated_at": null, "deleted_at": null}, {"id": 50, "name": "\u041d\u0430\u043c\u0430\u043d\u0433\u0430\u043d\u0441\u043a\u0438\u0439", "region_id": 5, "created_at": null, "updated_at": null, "deleted_at": null}, {"id": 51, "name": "\u041d\u0430\u0440\u044b\u043d\u0441\u043a\u0438\u0439", "region_id": 5, "created_at": null, "updated_at": null, "deleted_at": null}, {"id": 52, "name": "\u041f\u0430\u043f\u0441\u043a\u0438\u0439", "region_id": 5, "created_at": null, "updated_at": null, "deleted_at": null}, {"id": 53, "name": "\u0422\u0443\u0440\u0430\u043a\u0443\u0440\u0433\u0430\u043d\u0441\u043a\u0438\u0439", "region_id": 5, "created_at": null, "updated_at": null, "deleted_at": null}, {"id": 54, "name": "\u0423\u0439\u0447\u0438\u043d\u0441\u043a\u0438\u0439", "region_id": 5, "created_at": null, "updated_at": null, "deleted_at": null}, {"id": 55, "name": "\u0423\u0447\u043a\u0443\u0440\u0433\u0430\u043d\u0441\u043a\u0438\u0439", "region_id": 5, "created_at": null, "updated_at": null, "deleted_at": null}, {"id": 56, "name": "\u0427\u0430\u0440\u0442\u0430\u043a\u0441\u043a\u0438\u0439", "region_id": 5, "created_at": null, "updated_at": null, "deleted_at": null}, {"id": 57, "name": "\u0427\u0443\u0441\u0442\u0441\u043a\u0438\u0439", "region_id": 5, "created_at": null, "updated_at": null, "deleted_at": null}, {"id": 58, "name": "\u042f\u043d\u0433\u0438\u043a\u0443\u0440\u0433\u0430\u043d\u0441\u043a\u0438\u0439", "region_id": 5, "created_at": null, "updated_at": null, "deleted_at": null}, {"id": 59, "name": "\u0413\u0443\u0437\u0430\u0440\u0441\u043a\u0438\u0439", "region_id": 6, "created_at": null, "updated_at": null, "deleted_at": null}, {"id": 60, "name": "\u0414\u0435\u0445\u043a\u0430\u043d\u0430\u0431\u0430\u0434\u0441\u043a\u0438\u0439", "region_id": 6, "created_at": null, "updated_at": null, "deleted_at": null}, {"id": 61, "name": "\u041a\u0430\u043c\u0430\u0448\u0438\u043d\u0441\u043a\u0438\u0439", "region_id": 6, "created_at": null, "updated_at": null, "deleted_at": null}, {"id": 62, "name": "\u041a\u0430\u0440\u0448\u0438\u043d\u0441\u043a\u0438\u0439", "region_id": 6, "created_at": null, "updated_at": null, "deleted_at": null}, {"id": 63, "name": "\u041a\u0430\u0441\u0430\u043d\u0441\u043a\u0438\u0439", "region_id": 6, "created_at": null, "updated_at": null, "deleted_at": null}, {"id": 64, "name": "\u041a\u0430\u0441\u0431\u0438\u0439\u0441\u043a\u0438\u0439 (\u041a\u0430\u0441\u0431\u0438\u043d\u0441\u043a\u0438\u0439)", "region_id": 6, "created_at": null, "updated_at": null, "deleted_at": null}, {"id": 65, "name": "\u041a\u0438\u0442\u0430\u0431\u0441\u043a\u0438\u0439", "region_id": 6, "created_at": null, "updated_at": null, "deleted_at": null}, {"id": 66, "name": "\u041c\u0438\u0440\u0438\u0448\u043a\u043e\u0440\u0441\u043a\u0438\u0439", "region_id": 6, "created_at": null, "updated_at": null, "deleted_at": null}, {"id": 67, "name": "\u041c\u0443\u0431\u0430\u0440\u0435\u043a\u0441\u043a\u0438\u0439", "region_id": 6, "created_at": null, "updated_at": null, "deleted_at": null}, {"id": 68, "name": "\u041d\u0438\u0448\u0430\u043d\u0441\u043a\u0438\u0439", "region_id": 6, "created_at": null, "updated_at": null, "deleted_at": null}, {"id": 69, "name": "\u0427\u0438\u0440\u0430\u043a\u0447\u0438\u043d\u0441\u043a\u0438\u0439", "region_id": 6, "created_at": null, "updated_at": null, "deleted_at": null}, {"id": 70, "name": "\u0428\u0430\u0445\u0440\u0438\u0441\u0430\u0431\u0437\u0441\u043a\u0438\u0439", "region_id": 6, "created_at": null, "updated_at": null, "deleted_at": null}, {"id": 71, "name": "\u042f\u043a\u043a\u0430\u0431\u0430\u0433\u0441\u043a\u0438\u0439", "region_id": 6, "created_at": null, "updated_at": null, "deleted_at": null}, {"id": 72, "name": "\u0410\u043a\u0434\u0430\u0440\u044c\u0438\u043d\u0441\u043a\u0438\u0439", "region_id": 7, "created_at": null, "updated_at": null, "deleted_at": null}, {"id": 73, "name": "\u0411\u0443\u043b\u0443\u043d\u0433\u0443\u0440\u0441\u043a\u0438\u0439", "region_id": 7, "created_at": null, "updated_at": null, "deleted_at": null}, {"id": 74, "name": "\u0414\u0436\u0430\u043c\u0431\u0430\u0439\u0441\u043a\u0438\u0439", "region_id": 7, "created_at": null, "updated_at": null, "deleted_at": null}, {"id": 75, "name": "\u0418\u0448\u0442\u044b\u0445\u0430\u043d\u0441\u043a\u0438\u0439", "region_id": 7, "created_at": null, "updated_at": null, "deleted_at": null}, {"id": 76, "name": "\u041a\u0430\u0442\u0442\u0430\u043a\u0443\u0440\u0433\u0430\u043d\u0441\u043a\u0438\u0439", "region_id": 7, "created_at": null, "updated_at": null, "deleted_at": null}, {"id": 77, "name": "\u041a\u043e\u0448\u0440\u0430\u0431\u0430\u0434\u0441\u043a\u0438\u0439", "region_id": 7, "created_at": null, "updated_at": null, "deleted_at": null}, {"id": 78, "name": "\u041d\u0430\u0440\u043f\u0430\u0439\u0441\u043a\u0438\u0439", "region_id": 7, "created_at": null, "updated_at": null, "deleted_at": null}, {"id": 79, "name": "\u041d\u0443\u0440\u0430\u0431\u0430\u0434\u0441\u043a\u0438\u0439", "region_id": 7, "created_at": null, "updated_at": null, "deleted_at": null}, {"id": 80, "name": "\u041f\u0430\u0439\u0430\u0440\u044b\u043a\u0441\u043a\u0438\u0439", "region_id": 7, "created_at": null, "updated_at": null, "deleted_at": null}, {"id": 81, "name": "\u041f\u0430\u0441\u0442\u0434\u0430\u0440\u0433\u043e\u043c\u0441\u043a\u0438\u0439", "region_id": 7, "created_at": null, "updated_at": null, "deleted_at": null}, {"id": 82, "name": "\u041f\u0430\u0445\u0442\u0430\u0447\u0438\u0439\u0441\u043a\u0438\u0439", "region_id": 7, "created_at": null, "updated_at": null, "deleted_at": null}, {"id": 83, "name": "\u0421\u0430\u043c\u0430\u0440\u043a\u0430\u043d\u0434\u0441\u043a\u0438\u0439", "region_id": 7, "created_at": null, "updated_at": null, "deleted_at": null}, {"id": 84, "name": "\u0422\u0430\u0439\u043b\u0430\u043a\u0441\u043a\u0438\u0439", "region_id": 7, "created_at": null, "updated_at": null, "deleted_at": null}, {"id": 85, "name": "\u0423\u0440\u0433\u0443\u0442\u0441\u043a\u0438\u0439", "region_id": 7, "created_at": null, "updated_at": null, "deleted_at": null}, {"id": 86, "name": "\u0410\u043a\u0430\u043b\u0442\u044b\u043d\u0441\u043a\u0438\u0439", "region_id": 8, "created_at": null, "updated_at": null, "deleted_at": null}, {"id": 87, "name": "\u0411\u0430\u044f\u0443\u0442\u0441\u043a\u0438\u0439", "region_id": 8, "created_at": null, "updated_at": null, "deleted_at": null}, {"id": 88, "name": "\u0413\u0443\u043b\u0438\u0441\u0442\u0430\u043d\u0441\u043a\u0438\u0439", "region_id": 8, "created_at": null, "updated_at": null, "deleted_at": null}, {"id": 89, "name": "\u041c\u0438\u0440\u0437\u0430\u0430\u0431\u0430\u0434\u0441\u043a\u0438\u0439", "region_id": 8, "created_at": null, "updated_at": null, "deleted_at": null}, {"id": 90, "name": "\u0421\u0430\u0439\u0445\u0443\u043d\u0430\u0431\u0430\u0434\u0441\u043a\u0438\u0439", "region_id": 8, "created_at": null, "updated_at": null, "deleted_at": null}, {"id": 91, "name": "\u0421\u0430\u0440\u0434\u043e\u0431\u0438\u043d\u0441\u043a\u0438\u0439", "region_id": 8, "created_at": null, "updated_at": null, "deleted_at": null}, {"id": 92, "name": "\u0421\u044b\u0440\u0434\u0430\u0440\u044c\u0438\u043d\u0441\u043a\u0438\u0439", "region_id": 8, "created_at": null, "updated_at": null, "deleted_at": null}, {"id": 93, "name": "\u0425\u0430\u0432\u0430\u0441\u0442\u0441\u043a\u0438\u0439", "region_id": 8, "created_at": null, "updated_at": null, "deleted_at": null}, {"id": 94, "name": "\u0410\u043b\u0442\u044b\u043d\u0441\u0430\u0439\u0441\u043a\u0438\u0439", "region_id": 9, "created_at": null, "updated_at": null, "deleted_at": null}, {"id": 95, "name": "\u0410\u043d\u0433\u043e\u0440\u0441\u043a\u0438\u0439", "region_id": 9, "created_at": null, "updated_at": null, "deleted_at": null}, {"id": 96, "name": "\u0411\u0430\u0439\u0441\u0443\u043d\u0441\u043a\u0438\u0439", "region_id": 9, "created_at": null, "updated_at": null, "deleted_at": null}, {"id": 98, "name": "\u0414\u0435\u043d\u0430\u0443\u0441\u043a\u0438\u0439", "region_id": 9, "created_at": null, "updated_at": null, "deleted_at": null}, {"id": 99, "name": "\u0414\u0436\u0430\u0440\u043a\u0443\u0440\u0433\u0430\u043d\u0441\u043a\u0438\u0439", "region_id": 9, "created_at": null, "updated_at": null, "deleted_at": null}, {"id": 100, "name": "\u041a\u0438\u0437\u0438\u0440\u0438\u043a\u0441\u043a\u0438\u0439", "region_id": 9, "created_at": null, "updated_at": null, "deleted_at": null}, {"id": 101, "name": "\u041a\u0443\u043c\u043a\u0443\u0440\u0433\u0430\u043d\u0441\u043a\u0438\u0439", "region_id": 9, "created_at": null, "updated_at": null, "deleted_at": null}, {"id": 102, "name": "\u041c\u0443\u0437\u0440\u0430\u0431\u0430\u0434\u0441\u043a\u0438\u0439", "region_id": 9, "created_at": null, "updated_at": null, "deleted_at": null}, {"id": 103, "name": "\u0421\u0430\u0440\u0438\u0430\u0441\u0438\u0439\u0441\u043a\u0438\u0439", "region_id": 9, "created_at": null, "updated_at": null, "deleted_at": null}, {"id": 104, "name": "\u0422\u0435\u0440\u043c\u0435\u0437\u0441\u043a\u0438\u0439", "region_id": 9, "created_at": null, "updated_at": null, "deleted_at": null}, {"id": 105, "name": "\u0423\u0437\u0443\u043d\u0441\u043a\u0438\u0439", "region_id": 9, "created_at": null, "updated_at": null, "deleted_at": null}, {"id": 106, "name": "\u0428\u0435\u0440\u0430\u0431\u0430\u0434\u0441\u043a\u0438\u0439", "region_id": 9, "created_at": null, "updated_at": null, "deleted_at": null}, {"id": 107, "name": "\u0428\u0443\u0440\u0447\u0438\u043d\u0441\u043a\u0438\u0439", "region_id": 9, "created_at": null, "updated_at": null, "deleted_at": null}, {"id": 108, "name": "\u0410\u043a\u043a\u0443\u0440\u0433\u0430\u043d\u0441\u043a\u0438\u0439", "region_id": 10, "created_at": null, "updated_at": null, "deleted_at": null}, {"id": 109, "name": "\u0410\u0445\u0430\u043d\u0433\u0430\u0440\u0430\u043d\u0441\u043a\u0438\u0439", "region_id": 10, "created_at": null, "updated_at": null, "deleted_at": null}, {"id": 110, "name": "\u0411\u0435\u043a\u0430\u0431\u0430\u0434\u0441\u043a\u0438\u0439", "region_id": 10, "created_at": null, "updated_at": null, "deleted_at": null}, {"id": 111, "name": "\u0411\u043e\u0441\u0442\u0430\u043d\u043b\u044b\u043a\u0441\u043a\u0438\u0439", "region_id": 10, "created_at": null, "updated_at": null, "deleted_at": null}, {"id": 112, "name": "\u0411\u0443\u043a\u0438\u043d\u0441\u043a\u0438\u0439", "region_id": 10, "created_at": null, "updated_at": null, "deleted_at": null}, {"id": 113, "name": "\u0417\u0430\u043d\u0433\u0438\u0430\u0442\u0438\u043d\u0441\u043a\u0438\u0439", "region_id": 10, "created_at": null, "updated_at": null, "deleted_at": null}, {"id": 114, "name": "\u041a\u0438\u0431\u0440\u0430\u0439\u0441\u043a\u0438\u0439", "region_id": 10, "created_at": null, "updated_at": null, "deleted_at": null}, {"id": 115, "name": "\u041a\u0443\u0439\u0438\u0447\u0438\u0440\u0447\u0438\u043a\u0441\u043a\u0438\u0439", "region_id": 10, "created_at": null, "updated_at": null, "deleted_at": null}, {"id": 116, "name": "\u041f\u0430\u0440\u043a\u0435\u043d\u0442\u0441\u043a\u0438\u0439", "region_id": 10, "created_at": null, "updated_at": null, "deleted_at": null}, {"id": 117, "name": "\u041f\u0441\u043a\u0435\u043d\u0442\u0441\u043a\u0438\u0439", "region_id": 10, "created_at": null, "updated_at": null, "deleted_at": null}, {"id": 118, "name": "\u0423\u0440\u0442\u0430\u0447\u0438\u0440\u0447\u0438\u043a\u0441\u043a\u0438\u0439", "region_id": 10, "created_at": null, "updated_at": null, "deleted_at": null}, {"id": 119, "name": "\u0427\u0438\u043d\u0430\u0437\u0441\u043a\u0438\u0439", "region_id": 10, "created_at": null, "updated_at": null, "deleted_at": null}, {"id": 120, "name": "\u042e\u043a\u043e\u0440\u0438\u0447\u0438\u0440\u0447\u0438\u043a\u0441\u043a\u0438\u0439", "region_id": 10, "created_at": null, "updated_at": null, "deleted_at": null}, {"id": 121, "name": "\u042f\u043d\u0433\u0438\u044e\u043b\u044c\u0441\u043a\u0438\u0439", "region_id": 10, "created_at": null, "updated_at": null, "deleted_at": null}, {"id": 122, "name": "\u0422\u0430\u0448\u043a\u0435\u043d\u0442\u0441\u043a\u0438\u0439", "region_id": 10, "created_at": null, "updated_at": null, "deleted_at": null}, {"id": 123, "name": "\u0410\u043b\u0442\u044b\u0430\u0440\u044b\u043a\u0441\u043a\u0438\u0439", "region_id": 11, "created_at": null, "updated_at": null, "deleted_at": null}, {"id": 124, "name": "\u0411\u0430\u0433\u0434\u0430\u0434\u0441\u043a\u0438\u0439", "region_id": 11, "created_at": null, "updated_at": null, "deleted_at": null}, {"id": 125, "name": "\u0411\u0435\u0448\u0430\u0440\u044b\u043a\u0441\u043a\u0438\u0439", "region_id": 11, "created_at": null, "updated_at": null, "deleted_at": null}, {"id": 126, "name": "\u0411\u0443\u0432\u0430\u0439\u0434\u0438\u043d\u0441\u043a\u0438\u0439", "region_id": 11, "created_at": null, "updated_at": null, "deleted_at": null}, {"id": 127, "name": "\u0414\u0430\u043d\u0433\u0430\u0440\u0438\u043d\u0441\u043a\u0438\u0439", "region_id": 11, "created_at": null, "updated_at": null, "deleted_at": null}, {"id": 128, "name": "\u041a\u0443\u0432\u0438\u043d\u0441\u043a\u0438\u0439", "region_id": 11, "created_at": null, "updated_at": null, "deleted_at": null}, {"id": 129, "name": "\u041a\u0443\u0448\u0442\u0435\u043f\u0438\u043d\u0441\u043a\u0438\u0439", "region_id": 11, "created_at": null, "updated_at": null, "deleted_at": null}, {"id": 130, "name": "\u0420\u0438\u0448\u0442\u0430\u043d\u0441\u043a\u0438\u0439", "region_id": 11, "created_at": null, "updated_at": null, "deleted_at": null}, {"id": 131, "name": "\u0421\u043e\u0445\u0441\u043a\u0438\u0439", "region_id": 11, "created_at": null, "updated_at": null, "deleted_at": null}, {"id": 132, "name": "\u0422\u0430\u0448\u043b\u0430\u043a\u0441\u043a\u0438\u0439", "region_id": 11, "created_at": null, "updated_at": null, "deleted_at": null}, {"id": 133, "name": "\u0423\u0437\u0431\u0435\u043a\u0438\u0441\u0442\u0430\u043d\u0441\u043a\u0438\u0439", "region_id": 11, "created_at": null, "updated_at": null, "deleted_at": null}, {"id": 134, "name": "\u0423\u0447\u043a\u0443\u043f\u0440\u0438\u043a\u0441\u043a\u0438\u0439", "region_id": 11, "created_at": null, "updated_at": null, "deleted_at": null}, {"id": 135, "name": "\u0424\u0435\u0440\u0433\u0430\u043d\u0441\u043a\u0438\u0439", "region_id": 11, "created_at": null, "updated_at": null, "deleted_at": null}, {"id": 136, "name": "\u0424\u0443\u0440\u043a\u0430\u0442\u0441\u043a\u0438\u0439", "region_id": 11, "created_at": null, "updated_at": null, "deleted_at": null}, {"id": 137, "name": "\u042f\u0437\u044a\u044f\u0432\u0430\u043d\u0441\u043a\u0438\u0439", "region_id": 11, "created_at": null, "updated_at": null, "deleted_at": null}, {"id": 138, "name": "\u0411\u0430\u0433\u0430\u0442\u0441\u043a\u0438\u0439", "region_id": 12, "created_at": null, "updated_at": null, "deleted_at": null}, {"id": 139, "name": "\u0413\u0443\u0440\u043b\u0435\u043d\u0441\u043a\u0438\u0439", "region_id": 12, "created_at": null, "updated_at": null, "deleted_at": null}, {"id": 140, "name": "\u041a\u043e\u0448\u043a\u0443\u043f\u044b\u0440\u0441\u043a\u0438\u0439", "region_id": 12, "created_at": null, "updated_at": null, "deleted_at": null}, {"id": 141, "name": "\u0423\u0440\u0433\u0435\u043d\u0447\u0441\u043a\u0438\u0439", "region_id": 12, "created_at": null, "updated_at": null, "deleted_at": null}, {"id": 142, "name": "\u0425\u0430\u0437\u0430\u0440\u0430\u0441\u043f\u0441\u043a\u0438\u0439", "region_id": 12, "created_at": null, "updated_at": null, "deleted_at": null}, {"id": 143, "name": "\u0425\u0430\u043d\u043a\u0438\u043d\u0441\u043a\u0438\u0439", "region_id": 12, "created_at": null, "updated_at": null, "deleted_at": null}, {"id": 144, "name": "\u0425\u0438\u0432\u0438\u043d\u0441\u043a\u0438\u0439", "region_id": 12, "created_at": null, "updated_at": null, "deleted_at": null}, {"id": 145, "name": "\u0428\u0430\u0432\u0430\u0442\u0441\u043a\u0438\u0439", "region_id": 12, "created_at": null, "updated_at": null, "deleted_at": null}, {"id": 146, "name": "\u042f\u043d\u0433\u0438\u0430\u0440\u044b\u043a\u0441\u043a\u0438\u0439", "region_id": 12, "created_at": null, "updated_at": null, "deleted_at": null}, {"id": 147, "name": "\u042f\u043d\u0433\u0438\u0431\u0430\u0437\u0430\u0440\u0441\u043a\u0438\u0439", "region_id": 12, "created_at": null, "updated_at": null, "deleted_at": null}, {"id": 148, "name": "\u0410\u043c\u0443\u0434\u0430\u0440\u044c\u0438\u043d\u0441\u043a\u0438\u0439", "region_id": 13, "created_at": null, "updated_at": null, "deleted_at": null}, {"id": 149, "name": "\u0411\u0435\u0440\u0443\u043d\u0438\u0439\u0441\u043a\u0438\u0439", "region_id": 13, "created_at": null, "updated_at": null, "deleted_at": null}, {"id": 150, "name": "\u041a\u0430\u0440\u0430\u0443\u0437\u044f\u043a\u0441\u043a\u0438\u0439", "region_id": 13, "created_at": null, "updated_at": null, "deleted_at": null}, {"id": 151, "name": "\u041a\u0435\u0433\u0435\u0439\u043b\u0438\u0439\u0441\u043a\u0438\u0439", "region_id": 13, "created_at": null, "updated_at": null, "deleted_at": null}, {"id": 152, "name": "\u041a\u0443\u043d\u0433\u0440\u0430\u0434\u0441\u043a\u0438\u0439", "region_id": 13, "created_at": null, "updated_at": null, "deleted_at": null}, {"id": 153, "name": "\u041a\u0430\u043d\u043b\u044b\u043a\u0443\u043b\u044c\u0441\u043a\u0438\u0439", "region_id": 13, "created_at": null, "updated_at": null, "deleted_at": null}, {"id": 154, "name": "\u041c\u0443\u0439\u043d\u0430\u043a\u0441\u043a\u0438\u0439", "region_id": 13, "created_at": null, "updated_at": null, "deleted_at": null}, {"id": 155, "name": "\u041d\u0443\u043a\u0443\u0441\u0441\u043a\u0438\u0439", "region_id": 13, "created_at": null, "updated_at": null, "deleted_at": null}, {"id": 156, "name": "\u0422\u0430\u0445\u0442\u0430\u043a\u0443\u043f\u044b\u0440\u0441\u043a\u0438\u0439", "region_id": 13, "created_at": null, "updated_at": null, "deleted_at": null}, {"id": 157, "name": "\u0422\u0443\u0440\u0442\u043a\u0443\u043b\u044c\u0441\u043a\u0438\u0439", "region_id": 13, "created_at": null, "updated_at": null, "deleted_at": null}, {"id": 158, "name": "\u0425\u043e\u0434\u0436\u0435\u0439\u043b\u0438\u0439\u0441\u043a\u0438\u0439", "region_id": 13, "created_at": null, "updated_at": null, "deleted_at": null}, {"id": 159, "name": "\u0427\u0438\u043c\u0431\u0430\u0439\u0441\u043a\u0438\u0439", "region_id": 13, "created_at": null, "updated_at": null, "deleted_at": null}, {"id": 160, "name": "\u0428\u0443\u043c\u0430\u043d\u0430\u0439\u0441\u043a\u0438\u0439", "region_id": 13, "created_at": null, "updated_at": null, "deleted_at": null}, {"id": 161, "name": "\u042d\u043b\u043b\u0438\u043a\u043a\u0430\u043b\u0438\u043d\u0441\u043a\u0438\u0439", "region_id": 13, "created_at": null, "updated_at": null, "deleted_at": null}, {"id": 162, "name": "\u0410\u043b\u043c\u0430\u0437\u0430\u0440\u0441\u043a\u0438\u0439", "region_id": 14, "created_at": null, "updated_at": null, "deleted_at": null}, {"id": 163, "name": "\u0411\u0435\u043a\u0442\u0435\u043c\u0438\u0440\u0441\u043a\u0438\u0439", "region_id": 14, "created_at": null, "updated_at": null, "deleted_at": null}, {"id": 164, "name": "\u041c\u0438\u0440\u0430\u0431\u0430\u0434\u0441\u043a\u0438\u0439", "region_id": 14, "created_at": null, "updated_at": null, "deleted_at": null}, {"id": 165, "name": "\u041c\u0438\u0440\u0437\u043e-\u0423\u043b\u0443\u0433\u0431\u0435\u043a\u0441\u043a\u0438\u0439", "region_id": 14, "created_at": null, "updated_at": null, "deleted_at": null}, {"id": 166, "name": "\u0421\u0435\u0440\u0433\u0435\u043b\u0438\u0439\u0441\u043a\u0438\u0439", "region_id": 14, "created_at": null, "updated_at": null, "deleted_at": null}, {"id": 167, "name": "\u0423\u0447\u0442\u0435\u043f\u0438\u043d\u0441\u043a\u0438\u0439", "region_id": 14, "created_at": null, "updated_at": null, "deleted_at": null}, {"id": 168, "name": "\u0427\u0438\u043b\u0430\u043d\u0437\u0430\u0440\u0441\u043a\u0438\u0439", "region_id": 14, "created_at": null, "updated_at": null, "deleted_at": null}, {"id": 169, "name": "\u0428\u0430\u0439\u0445\u0430\u043d\u0442\u0430\u0445\u0443\u0440\u0441\u043a\u0438\u0439", "region_id": 14, "created_at": null, "updated_at": null, "deleted_at": null}, {"id": 170, "name": "\u042e\u043d\u0443\u0441\u0430\u0431\u0430\u0434\u0441\u043a\u0438\u0439", "region_id": 14, "created_at": null, "updated_at": null, "deleted_at": null}, {"id": 171, "name": "\u042f\u043a\u043a\u0430\u0441\u0430\u0440\u0430\u0439\u0441\u043a\u0438\u0439", "region_id": 14, "created_at": null, "updated_at": null, "deleted_at": null}, {"id": 172, "name": "\u042f\u0448\u043d\u0430\u0431\u0430\u0434\u0441\u043a\u0438\u0439", "region_id": 14, "created_at": null, "updated_at": null, "deleted_at": null}, {"id": 173, "name": "\u0433\u043e\u0440\u043e\u0434 \u0410\u043d\u0434\u0438\u0436\u0430\u043d", "region_id": 1, "created_at": null, "updated_at": null, "deleted_at": null}, {"id": 174, "name": "\u0433\u043e\u0440\u043e\u0434 \u0411\u0443\u0445\u0430\u0440\u0430", "region_id": 2, "created_at": null, "updated_at": null, "deleted_at": null}, {"id": 175, "name": "\u0433\u043e\u0440\u043e\u0434 \u0414\u0436\u0438\u0437\u0430\u043a", "region_id": 3, "created_at": null, "updated_at": null, "deleted_at": null}, {"id": 176, "name": "\u0433\u043e\u0440\u043e\u0434 \u041d\u0430\u0432\u043e\u0438", "region_id": 4, "created_at": null, "updated_at": null, "deleted_at": null}, {"id": 177, "name": "\u0433\u043e\u0440\u043e\u0434 \u041d\u0430\u043c\u0430\u043d\u0433\u0430\u043d", "region_id": 5, "created_at": null, "updated_at": null, "deleted_at": null}, {"id": 178, "name": "\u0433\u043e\u0440\u043e\u0434 \u041a\u0430\u0440\u0448\u0438", "region_id": 6, "created_at": null, "updated_at": null, "deleted_at": null}, {"id": 179, "name": "\u0433\u043e\u0440\u043e\u0434 \u0421\u0430\u043c\u0430\u0440\u043a\u0430\u043d\u0434", "region_id": 7, "created_at": null, "updated_at": null, "deleted_at": null}, {"id": 180, "name": "\u0433\u043e\u0440\u043e\u0434 \u0413\u0443\u043b\u0438\u0441\u0442\u0430\u043d", "region_id": 8, "created_at": null, "updated_at": null, "deleted_at": null}, {"id": 181, "name": "\u0433\u043e\u0440\u043e\u0434 \u041d\u0443\u0440\u0430\u0444\u0448\u043e\u043d", "region_id": 10, "created_at": null, "updated_at": null, "deleted_at": null}, {"id": 182, "name": "\u0433\u043e\u0440\u043e\u0434 \u0424\u0435\u0440\u0433\u0430\u043d\u0430", "region_id": 11, "created_at": null, "updated_at": null, "deleted_at": null}, {"id": 183, "name": "\u0433\u043e\u0440\u043e\u0434 \u0422\u0435\u0440\u043c\u0435\u0437", "region_id": 9, "created_at": null, "updated_at": null, "deleted_at": null}, {"id": 184, "name": "\u0433\u043e\u0440\u043e\u0434 \u0423\u0440\u0433\u0435\u043d\u0447", "region_id": 12, "created_at": null, "updated_at": null, "deleted_at": null}, {"id": 185, "name": "\u0433\u043e\u0440\u043e\u0434 \u041d\u0443\u043a\u0443\u0441", "region_id": 13, "created_at": null, "updated_at": null, "deleted_at": null}, {"id": 186, "name": "\u0411\u0430\u043d\u0434\u0438\u0445\u0430\u043d", "region_id": 9, "created_at": null, "updated_at": null, "deleted_at": null}, {"id": 187, "name": "\u0433\u043e\u0440\u043e\u0434 \u041c\u0430\u0440\u0433\u0438\u043b\u0430\u043d", "region_id": 11, "created_at": null, "updated_at": null, "deleted_at": null}, {"id": 188, "name": "\u0433\u043e\u0440\u043e\u0434 \u041a\u0443\u0432\u0430\u0441\u0430\u0439", "region_id": 11, "created_at": null, "updated_at": null, "deleted_at": null}, {"id": 189, "name": "\u0433\u043e\u0440\u043e\u0434 \u041a\u043e\u043a\u0430\u043d\u0434", "region_id": 11, "created_at": null, "updated_at": null, "deleted_at": null}, {"id": 190, "name": "\u0411\u043e\u0437\u0430\u0442\u0430\u0443", "region_id": 13, "created_at": null, "updated_at": null, "deleted_at": null}, {"id": 191, "name": "\u0422\u0430\u0445\u0438\u0430\u0442\u0430\u0448", "region_id": 13, "created_at": null, "updated_at": null, "deleted_at": null}, {"id": 195, "name": "\u0433\u043e\u0440\u043e\u0434  \u041a\u0430\u0442\u0442\u0430\u043a\u0443\u0440\u0433\u0430\u043d", "region_id": 7, "created_at": null, "updated_at": null, "deleted_at": null}, {"id": 196, "name": "\u0433\u043e\u0440\u043e\u0434 \u0425\u0430\u043d\u0430\u0431\u0430\u0434", "region_id": 1, "created_at": null, "updated_at": null, "deleted_at": null}, {"id": 197, "name": "\u0433\u043e\u0440\u043e\u0434 \u0425\u0438\u0432\u0430", "region_id": 12, "created_at": null, "updated_at": null, "deleted_at": null}, {"id": 198, "name": "\u0422\u0443\u043f\u0440\u0430\u043a\u043a\u0430\u043b\u0438\u043d\u0441\u043a\u0438\u0439", "region_id": 12, "created_at": null, "updated_at": null, "deleted_at": null}, {"id": 199, "name": "\u0433\u043e\u0440\u043e\u0434 \u041a\u0430\u0433\u0430\u043d", "region_id": 2, "created_at": null, "updated_at": null, "deleted_at": null}, {"id": 200, "name": "\u0433\u043e\u0440\u043e\u0434 \u0417\u0430\u0440\u0430\u0444\u0448\u0430\u043d", "region_id": 4, "created_at": null, "updated_at": null, "deleted_at": null}, {"id": 201, "name": "\u0433\u043e\u0440\u043e\u0434 \u0492\u043e\u0437\u0493\u043e\u043d", "region_id": 4, "created_at": null, "updated_at": null, "deleted_at": null}, {"id": 204, "name": "\u0433\u043e\u0440\u043e\u0434 \u0410\u043d\u0433\u0440\u0435\u043d", "region_id": 10, "created_at": null, "updated_at": null, "deleted_at": null}, {"id": 205, "name": "\u0433\u043e\u0440\u043e\u0434 \u0411\u0435\u043a\u0430\u0431\u0430\u0434", "region_id": 10, "created_at": null, "updated_at": null, "deleted_at": null}, {"id": 202, "name": "\u0433\u043e\u0440\u043e\u0434 \u042f\u043d\u0433\u0438\u0435\u0440", "region_id": 8, "created_at": null, "updated_at": null, "deleted_at": null}, {"id": 203, "name": "\u0433\u043e\u0440\u043e\u0434 \u0428\u0438\u0440\u0438\u043d", "region_id": 8, "created_at": null, "updated_at": null, "deleted_at": null}, {"id": 206, "name": "\u0433\u043e\u0440\u043e\u0434 \u0427\u0438\u0440\u0447\u0438\u043a", "region_id": 10, "created_at": null, "updated_at": null, "deleted_at": null}, {"id": 207, "name": "\u0433\u043e\u0440\u043e\u0434 \u0410\u043b\u043c\u0430\u043b\u044b\u043a", "region_id": 10, "created_at": null, "updated_at": null, "deleted_at": null}, {"id": 208, "name": "\u0433\u043e\u0440\u043e\u0434 \u0410\u0445\u0430\u043d\u0433\u0430\u0440\u0430\u043d", "region_id": 10, "created_at": null, "updated_at": null, "deleted_at": null}, {"id": 209, "name": "\u0433\u043e\u0440\u043e\u0434 \u042f\u043d\u0433\u0438\u044e\u043b\u044c", "region_id": 10, "created_at": null, "updated_at": null, "deleted_at": null}, {"id": 210, "name": "\u042f\u043d\u0433\u0438\u0445\u0430\u0451\u0442\u0441\u043a\u0438\u0439", "region_id": 14, "created_at": null, "updated_at": null, "deleted_at": null}], "object_types": [{"id": 1, "name": "\u0421\u0442\u0440\u043e\u0438\u0442\u0435\u043b\u044c\u0441\u0442\u0432\u043e \u0434\u043e\u0440\u043e\u0433, \u043c\u043e\u0441\u0442\u043e\u0432, \u043f\u0443\u0442\u0435\u043f\u0440\u043e\u0432\u043e\u0434\u043e\u0432 \u0438 \u0436\u0435\u043b\u0435\u0437\u043d\u044b\u0445 \u0434\u043e\u0440\u043e\u0433", "created_at": null, "updated_at": null}, {"id": 2, "name": "\u0421\u043e\u0446\u0438\u0430\u043b\u044c\u043d\u044b\u0435 \u043e\u0431\u044a\u0435\u043a\u0442\u044b", "created_at": null, "updated_at": null}, {"id": 3, "name": "\u0418\u043d\u0436\u0435\u043d\u0435\u0440\u043d\u044b\u0435 \u0441\u0435\u0442\u0438", "created_at": null, "updated_at": null}, {"id": 4, "name": "\u041c\u0435\u043b\u0438\u043e\u0440\u0430\u0446\u0438\u044f \u0438 \u043e\u0440\u043e\u0448\u0435\u043d\u0438\u0435 \u0437\u0435\u043c\u0435\u043b\u044c", "created_at": null, "updated_at": null}, {"id": 5, "name": "\u041d\u0435\u0444\u0442\u0435\u0433\u0430\u0437\u043e\u0432\u0430\u044f \u043f\u0440\u043e\u043c\u044b\u0448\u043b\u0435\u043d\u043d\u043e\u0441\u0442\u044c", "created_at": null, "updated_at": null}], "service_types": [{"id": 1, "name": "\u0420\u0435\u043c\u043e\u043d\u0442", "created_at": null, "updated_at": null}, {"id": 2, "name": "\u0420\u0435\u043a\u043e\u043d\u0441\u0442\u0440\u0443\u043a\u0446\u0438\u044f", "created_at": null, "updated_at": null}, {"id": 3, "name": "\u0421\u0442\u0440\u043e\u0438\u0442\u0435\u043b\u044c\u0441\u0442\u0432\u043e", "created_at": null, "updated_at": null}], "today_ends": 0}, "code": 200}